projects/template/vsrc/top.v
`timescale 1ps/1ps
module top(
  input a,
  input b,
  output f
);
    initial begin
        $dumpfile("./vlt_dump.vcd");
        $dumpvars(1,xor_gate);
    end
    assign f = a ^ b;
endmodule

projects/template/vlt_dump.vcd
$version Generated by VerilatedVcd $end
$date Tue Apr  5 19:37:21 2022 $end
$timescale 1ps $end

 $scope module TOP $end
  $var wire  1 # a $end
  $var wire  1 $ b $end
  $var wire  1 % f $end
  $scope module top $end
   $var wire  1 # a $end
   $var wire  1 $ b $end
   $var wire  1 % f $end
  $upscope $end
 $upscope $end
$enddefinitions $end


#0
1#
0$
1%
#1
1$
0%
#2
#3
0#
0$
#4
1#
1$
#5
0#
1%
#6
#7
1#
0$
#8
0#
0%
#9
#10
1#
1%
#11
1$
0%
#12
0#
0$
#13
1$
1%
#14
1#
0%
#15
0$
1%
#16
0#
0%
#17
1#
1$
#18
0$
1%
#19
#20
1$
0%
#21
#22
0#
1%
#23
0$
0%
#24
1#
1%
#25
#26
#27
0#
1$
#28
0$
0%
#29
1$
1%
#30
1#
0%
#31
0#
1%
#32
#33
#34
1#
0%
#35
0#
1%
#36
#37
#38
0$
0%
#39
1#
1%
#40
#41
0#
0%
#42
#43
1#
1$
#44
0#
1%
#45
0$
0%
#46
#47
1#
1%
#48
0#
0%
#49
1$
1%
#50
1#
0$
#51
0#
0%
#52
1#
1$
#53
0$
1%
#54
#55
0#
0%
#56
1#
1%
#57
0#
1$
#58
1#
0%
#59
0#
1%
#60
#61
1#
0%
#62
#63
#64
#65
0$
1%
#66
1$
0%
#67
0#
1%
#68
#69
1#
0$
#70
0#
1$
#71
#72
1#
0%
#73
0#
0$
#74
1$
1%
#75
#76
#77
#78
#79
1#
0%
#80
0$
1%
#81
0#
0%
#82
1#
1%
#83
#84
0#
0%
#85
#86
1#
1%
#87
1$
0%
#88
#89
0$
1%
#90
0#
1$
#91
1#
0$
#92
1$
0%
#93
0#
1%
#94
#95
1#
0%
#96
#97
0#
0$
#98
1#
1$
#99
0#
1%
#100
0$
0%
#101
1#
1$
#102
0$
1%
#103
0#
0%
#104
#105
#106
1#
1$
#107
0$
1%
#108
0#
1$
#109
#110
#111
#112
0$
0%
#113
1#
1$
#114
0#
0$
#115
1#
1%
#116
0#
0%
#117
1#
1$
#118
0$
1%
#119
0#
1$
#120
0$
0%
#121
1#
1$
#122
0#
0$
#123
#124
1#
1%
#125
1$
0%
#126
0$
1%
#127
0#
1$
#128
0$
0%
#129
#130
1$
1%
#131
0$
0%
#132
#133
1$
1%
#134
0$
0%
#135
#136
1$
1%
#137
1#
0$
#138
0#
1$
#139
1#
0%
#140
0$
1%
#141
#142
0#
1$
#143
1#
0%
#144
0$
1%
#145
1$
0%
#146
0$
1%
#147
0#
1$
#148
0$
0%
#149
#150
#151
#152
1$
1%
#153
1#
0$
#154
#155
#156
0#
0%
#157
1#
1$
#158
0#
0$
#159
1$
1%
#160
#161
1#
0$
#162
1$
0%
#163
#164
0$
1%
#165
1$
0%
#166
0#
1%
#167
1#
0$
#168
#169
0#
0%
#170
#171
1$
1%
#172
#173
0$
0%
#174
#175
#176
1#
1$
#177
0#
1%
#178
0$
0%
#179
1$
1%
#180
0$
0%
#181
#182
1#
1$
#183
0$
1%
#184
0#
1$
#185
0$
0%
#186
1#
1$
#187
0$
1%
#188
0#
1$
#189
0$
0%
#190
1#
1%
#191
1$
0%
#192
#193
0#
1%
#194
1#
0$
#195
0#
1$
#196
0$
0%
#197
#198
1$
1%
#199
0$
0%
#200
1$
1%
#201
0$
0%
#202
#203
#204
1#
1%
#205
1$
0%
#206
0$
1%
#207
0#
0%
#208
1#
1%
#209
0#
1$
#210
0$
0%
#211
1$
1%
#212
1#
0$
#213
1$
0%
#214
#215
0$
1%
#216
0#
1$
#217
0$
0%
#218
1#
1%
#219
1$
0%
#220
0#
0$
#221
1$
1%
#222
0$
0%
#223
1$
1%
#224
0$
0%
#225
#226
1$
1%
#227
1#
0%
#228
0$
1%
#229
0#
1$
#230
#231
1#
0$
#232
1$
0%
#233
0$
1%
#234
#235
1$
0%
#236
0#
1%
#237
1#
0$
#238
1$
0%
#239
#240
0$
1%
#241
0#
1$
#242
1#
0%
#243
0$
1%
#244
0#
1$
#245
1#
0$
#246
#247
0#
0%
#248
1#
1$
#249
0#
0$
#250
1#
1%
#251
0#
1$
#252
1#
0%
#253
#254
0#
1%
#255
#256
1#
0$
#257
0#
0%
#258
1$
1%
#259
0$
0%
#260
1#
1%
#261
0#
0%
#262
#263
#264
#265
1$
1%
#266
0$
0%
#267
1#
1%
#268
#269
1$
0%
#270
#271
0#
0$
#272
1$
1%
#273
0$
0%
#274
1$
1%
#275
#276
1#
0$
#277
1$
0%
#278
0#
1%
#279
1#
0$
#280
0#
0%
#281
#282
1$
1%
#283
0$
0%
#284
1#
1$
#285
#286
0$
1%
#287
1$
0%
#288
0$
1%
#289
1$
0%
#290
#291
0$
1%
#292
#293
1$
0%
#294
0#
1%
#295
0$
0%
#296
1#
1%
#297
0#
1$
#298
1#
0%
#299
0$
1%
#300
0#
1$
#301
1#
0%
#302
#303
0#
0$
#304
1#
1$
#305
0$
1%
#306
0#
0%
#307
1$
1%
#308
1#
0%
#309
#310
0#
1%
#311
1#
0%
#312
#313
0$
1%
#314
0#
0%
#315
1$
1%
#316
1#
0$
#317
0#
0%
#318
1#
1$
#319
0#
0$
#320
#321
1$
1%
#322
0$
0%
#323
1$
1%
#324
1#
0%
#325
0#
0$
#326
1$
1%
#327
1#
0%
#328
0$
1%
#329
1$
0%
#330
0$
1%
#331
0#
0%
#332
1$
1%
#333
1#
0%
#334
0#
1%
#335
1#
0$
#336
1$
0%
#337
0$
1%
#338
#339
#340
#341
0#
0%
#342
1#
1%
#343
#344
0#
1$
#345
#346
1#
0$
#347
0#
1$
#348
1#
0%
#349
0#
1%
#350
#351
0$
0%
#352
1$
1%
#353
#354
1#
0%
#355
#356
0$
1%
#357
1$
0%
#358
0#
0$
#359
1#
1%
#360
1$
0%
#361
0#
0$
#362
#363
1#
1$
#364
#365
#366
0#
1%
#367
1#
0$
#368
0#
1$
#369
1#
0$
#370
1$
0%
#371
0$
1%
#372
#373
1$
0%
#374
0#
1%
#375
1#
0$
#376
0#
1$
#377
0$
0%
#378
1#
1%
#379
0#
0%
#380
1#
1$
#381
0#
0$
#382
1$
1%
#383
0$
0%
#384
1#
1%
#385
0#
0%
#386
1#
1$
#387
0#
0$
#388
1#
1%
#389
#390
#391
0#
1$
#392
0$
0%
#393
1$
1%
#394
0$
0%
#395
#396
1#
1%
#397
0#
1$
#398
1#
0$
#399
#400
0#
0%
#401
1$
1%
#402
1#
0%
#403
#404
0$
1%
#405
#406
1$
0%
#407
#408
#409
0#
0$
#410
1#
1%
#411
0#
0%
#412
#413
1#
1%
#414
0#
1$
#415
#416
1#
0%
#417
0#
0$
#418
#419
1#
1$
#420
0#
0$
#421
1#
1$
#422
0$
1%
#423
0#
1$
#424
#425
1#
0%
#426
#427
0#
0$
#428
1#
1$
#429
0#
1%
#430
0$
0%
#431
1$
1%
#432
1#
0%
#433
0#
1%
#434
1#
0%
#435
0#
1%
#436
#437
1#
0%
#438
0#
1%
#439
0$
0%
#440
1$
1%
#441
1#
0$
#442
0#
1$
#443
#444
1#
0$
#445
1$
0%
#446
0#
1%
#447
1#
0$
#448
0#
1$
#449
1#
0%
#450
0#
0$
#451
1#
1%
#452
#453
0#
1$
#454
1#
0$
#455
#456
0#
1$
#457
0$
0%
#458
#459
1$
1%
#460
#461
1#
0$
#462
0#
0%
#463
1$
1%
#464
1#
0$
#465
0#
1$
#466
#467
#468
1#
0$
#469
1$
0%
#470
0#
0$
#471
1#
1%
#472
1$
0%
#473
0$
1%
#474
1$
0%
#475
#476
0#
0$
#477
1#
1%
#478
0#
0%
#479
1#
1$
#480
0#
0$
#481
1#
1%
#482
1$
0%
#483
#484
0$
1%
#485
0#
1$
#486
1#
0%
#487
0#
0$
#488
1$
1%
#489
#490
0$
0%
#491
#492
1$
1%
#493
#494
1#
0$
#495
0#
1$
#496
#497
1#
0%
#498
0#
1%
#499
#500
1#
0$
#501
#502
1$
0%
#503
#504
0#
1%
#505
0$
0%
#506
1#
1%
#507
0#
0%
#508
#509
1#
1$
#510
0#
1%
#511
1#
0$
#512
#513
0#
1$
#514
1#
0$
#515
1$
0%
#516
0$
1%
#517
#518
#519
0#
1$
#520
0$
0%
#521
1#
1$
#522
#523
#524
0$
1%
#525
0#
0%
#526
1$
1%
#527
#528
0$
0%
#529
1$
1%
#530
1#
0%
#531
0#
0$
#532
1#
1%
#533
0#
0%
#534
#535
1#
1%
#536
#537
0#
0%
#538
1#
1$
#539
#540
0#
1%
#541
1#
0$
#542
1$
0%
#543
#544
0#
1%
#545
#546
1#
0%
#547
0$
1%
#548
1$
0%
#549
#550
0#
0$
#551
1$
1%
#552
1#
0$
#553
#554
#555
1$
0%
#556
0$
1%
#557
#558
0#
0%
#559
1#
1%
#560
0#
0%
#561
1#
1$
#562
0$
1%
#563
#564
#565
1$
0%
#566
#567
0#
0$
#568
1#
1$
#569
0#
1%
#570
1#
0$
#571
0#
1$
#572
0$
0%
#573
1#
1%
#574
0#
1$
#575
0$
0%
#576
1#
1$
#577
0$
1%
#578
1$
0%
#579
0#
1%
#580
1#
0%
#581
0#
0$
#582
1#
1$
#583
0#
0$
#584
1$
1%
#585
1#
0$
#586
#587
1$
0%
#588
0#
0$
#589
#590
1#
1%
#591
#592
0#
0%
#593
1$
1%
#594
1#
0$
#595
0#
1$
#596
#597
1#
0%
#598
0#
0$
#599
1#
1%
#600
1$
0%
#601
0#
0$
#602
1#
1$
#603
#604
0#
1%
#605
1#
0%
#606
0#
0$
#607
#608
1#
1%
#609
#610
#611
1$
0%
#612
#613
0#
1%
#614
1#
0%
#615
0$
1%
#616
0#
0%
#617
1$
1%
#618
1#
0%
#619
0#
1%
#620
1#
0$
#621
1$
0%
#622
0#
1%
#623
1#
0%
#624
0$
1%
#625
0#
0%
#626
1$
1%
#627
1#
0%
#628
0#
1%
#629
#630
1#
0$
#631
1$
0%
#632
0#
1%
#633
1#
0%
#634
#635
0$
1%
#636
#637
#638
#639
#640
0#
1$
#641
1#
0%
#642
0$
1%
#643
0#
1$
#644
#645
1#
0%
#646
0$
1%
#647
0#
1$
#648
#649
#650
1#
0%
#651
0$
1%
#652
#653
0#
0%
#654
#655
1#
1%
#656
#657
#658
0#
0%
#659
#660
1#
1$
#661
0$
1%
#662
#663
1$
0%
#664
#665
0#
0$
#666
1#
1$
#667
0$
1%
#668
1$
0%
#669
#670
0$
1%
#671
0#
1$
#672
#673
1#
0$
#674
1$
0%
#675
0$
1%
#676
0#
0%
#677
#678
1$
1%
#679
1#
0$
#680
#681
0#
0%
#682
1#
1$
#683
0#
1%
#684
1#
0%
#685
0#
0$
#686
1#
1%
#687
1$
0%
#688
0#
1%
#689
#690
#691
#692
1#
0$
#693
#694
0#
0%
#695
1$
1%
#696
0$
0%
#697
1#
1%
#698
0#
1$
#699
1#
0%
#700
#701
0$
1%
#702
0#
1$
#703
0$
0%
#704
#705
1#
1%
#706
1$
0%
#707
0$
1%
#708
0#
0%
#709
#710
1#
1%
#711
1$
0%
#712
0$
1%
#713
1$
0%
#714
0$
1%
#715
0#
0%
#716
1$
1%
#717
1#
0$
#718
0#
1$
#719
0$
0%
#720
1#
1$
#721
0$
1%
#722
#723
0#
1$
#724
1#
0%
#725
0$
1%
#726
#727
#728
0#
1$
#729
1#
0%
#730
#731
0#
1%
#732
1#
0%
#733
#734
0#
1%
#735
#736
1#
0%
#737
0$
1%
#738
1$
0%
#739
0$
1%
#740
0#
0%
#741
#742
#743
#744
1#
1%
#745
#746
1$
0%
#747
0#
0$
#748
1$
1%
#749
0$
0%
#750
1#
1%
#751
#752
#753
0#
0%
#754
1$
1%
#755
1#
0$
#756
1$
0%
#757
0#
1%
#758
1#
0%
#759
0$
1%
#760
#761
#762
0#
1$
#763
1#
0$
#764
0#
1$
#765
1#
0%
#766
0$
1%
#767
#768
1$
0%
#769
0#
1%
#770
#771
1#
0%
#772
0$
1%
#773
0#
0%
#774
1#
1$
#775
0$
1%
#776
0#
0%
#777
#778
1#
1$
#779
0#
1%
#780
#781
1#
0%
#782
0#
0$
#783
1#
1$
#784
0#
0$
#785
#786
1#
1$
#787
0#
0$
#788
1#
1%
#789
#790
0#
0%
#791
#792
1$
1%
#793
#794
0$
0%
#795
1$
1%
#796
#797
0$
0%
#798
#799
1#
1%
#800
0#
1$
#801
#802
0$
0%
#803
#804
1#
1$
#805
0#
1%
#806
1#
0%
#807
#808
0#
1%
#809
0$
0%
#810
1#
1%
#811
1$
0%
#812
0#
0$
#813
1#
1%
#814
0#
0%
#815
#816
1#
1%
#817
#818
1$
0%
#819
0#
0$
#820
#821
1#
1$
#822
0$
1%
#823
0#
1$
#824
1#
0$
#825
0#
0%
#826
1#
1$
#827
0#
1%
#828
1#
0%
#829
#830
0#
1%
#831
1#
0%
#832
#833
0$
1%
#834
0#
1$
#835
#836
#837
#838
1#
0%
#839
0$
1%
#840
1$
0%
#841
0$
1%
#842
0#
1$
#843
1#
0$
#844
0#
0%
#845
1#
1%
#846
1$
0%
#847
0#
1%
#848
#849
1#
0$
#850
#851
1$
0%
#852
0$
1%
#853
0#
1$
#854
1#
0%
#855
0$
1%
#856
0#
0%
#857
1#
1$
#858
0$
1%
#859
#860
#861
0#
0%
#862
1#
1%
#863
1$
0%
#864
0#
1%
#865
#866
1#
0%
#867
0#
0$
#868
1#
1%
#869
#870
0#
1$
#871
1#
0$
#872
#873
1$
0%
#874
0#
0$
#875
1#
1$
#876
#877
0#
0$
#878
1$
1%
#879
0$
0%
#880
#881
1#
1$
#882
#883
0#
1%
#884
1#
0%
#885
#886
0#
0$
#887
#888
1$
1%
#889
1#
0%
#890
0#
0$
#891
1$
1%
#892
1#
0$
#893
1$
0%
#894
0#
1%
#895
1#
0$
#896
#897
0#
1$
#898
1#
0$
#899
0#
1$
#900
1#
0%
#901
0#
0$
#902
#903
#904
1$
1%
#905
1#
0$
#906
#907
#908
0#
0%
#909
#910
1$
1%
#911
1#
0%
#912
0#
1%
#913
#914
1#
0$
#915
0#
0%
#916
1$
1%
#917
0$
0%
#918
1#
1%
#919
0#
1$
#920
1#
0$
#921
#922
0#
0%
#923
1#
1%
#924
1$
0%
#925
#926
0#
0$
#927
#928
1#
1$
#929
0#
0$
#930
1#
1%
#931
0#
1$
#932
1#
0%
#933
#934
0$
1%
#935
0#
1$
#936
0$
0%
#937
1#
1%
#938
0#
0%
#939
1$
1%
#940
1#
0%
#941
0#
0$
#942
1#
1$
#943
0#
0$
#944
#945
1$
1%
#946
1#
0%
#947
0$
1%
#948
0#
0%
#949
1#
1$
#950
0#
0$
#951
#952
#953
#954
1$
1%
#955
0$
0%
#956
#957
#958
1#
1%
#959
0#
1$
#960
1#
0%
#961
0$
1%
#962
0#
0%
#963
#964
#965
1#
1$
#966
0#
0$
#967
1#
1%
#968
0#
0%
#969
#970
1#
1%
#971
0#
1$
#972
1#
0$
#973
#974
#975
0#
0%
#976
1#
1$
#977
0#
1%
#978
1#
0$
#979
1$
0%
#980
0#
0$
#981
#982
#983
#984
1$
1%
#985
1#
0%
#986
#987
0#
0$
#988
#989
1#
1$
#990
0#
1%
#991
1#
0%
#992
0#
1%
#993
#994
1#
0%
#995
0#
0$
#996
1#
1$
#997
0#
0$
#998
1#
1$
#999
0#
1%
#1000
#1001
#1002
1#
0$
#1003
0#
1$
#1004
#1005
0$
0%
#1006
1$
1%
#1007
1#
0$
#1008
0#
1$
#1009
1#
0%
#1010
0#
1%
#1011
1#
0$
#1012
0#
0%
#1013
1$
1%
#1014
1#
0$
#1015
0#
1$
#1016
0$
0%
#1017
1$
1%
#1018
1#
0$
#1019
0#
1$
#1020
1#
0$
#1021
0#
1$
#1022
1#
0%
#1023
#1024
0$
1%
#1025
0#
1$
#1026
0$
0%
#1027
1#
1%
#1028
0#
1$
#1029
#1030
0$
0%
#1031
#1032
1#
1%
#1033
#1034
1$
0%
#1035
0$
1%
#1036
1$
0%
#1037
0#
0$
#1038
1#
1$
#1039
0$
1%
#1040
0#
1$
#1041
1#
0$
#1042
1$
0%
#1043
0#
1%
#1044
0$
0%
#1045
#1046
1#
1%
#1047
0#
0%
#1048
1#
1$
#1049
0#
0$
#1050
1$
1%
#1051
#1052
1#
0$
#1053
#1054
0#
0%
#1055
#1056
1$
1%
#1057
#1058
0$
0%
#1059
1#
1$
#1060
#1061
0$
1%
#1062
0#
0%
#1063
1$
1%
#1064
1#
0$
#1065
#1066
1$
0%
#1067
0$
1%
#1068
0#
1$
#1069
0$
0%
#1070
1#
1%
#1071
0#
1$
#1072
0$
0%
#1073
1#
1%
#1074
0#
0%
#1075
1#
1$
#1076
#1077
#1078
#1079
0#
0$
#1080
1#
1$
#1081
0#
1%
#1082
1#
0$
#1083
1$
0%
#1084
0$
1%
#1085
#1086
0#
1$
#1087
0$
0%
#1088
1#
1$
#1089
#1090
0$
1%
#1091
#1092
#1093
0#
0%
#1094
#1095
1#
1$
#1096
0#
1%
#1097
#1098
1#
0$
#1099
0#
0%
#1100
1$
1%
#1101
1#
0$
#1102
0#
1$
#1103
1#
0%
#1104
0#
0$
#1105
1$
1%
#1106
#1107
1#
0$
#1108
0#
1$
#1109
0$
0%
#1110
1$
1%
#1111
1#
0$
#1112
#1113
#1114
0#
1$
#1115
1#
0$
#1116
0#
0%
#1117
#1118
1#
1$
#1119
#1120
#1121
0#
0$
#1122
1#
1$
#1123
0#
1%
#1124
1#
0$
#1125
1$
0%
#1126
0#
0$
#1127
1#
1$
#1128
0#
0$
#1129
1#
1%
#1130
#1131
0#
1$
#1132
#1133
1#
0%
#1134
0#
0$
#1135
#1136
1#
1%
#1137
0#
0%
#1138
#1139
1#
1$
#1140
0#
0$
#1141
#1142
1#
1$
#1143
#1144
#1145
0#
0$
#1146
1#
1%
#1147
#1148
#1149
#1150
0#
0%
#1151
1$
1%
#1152
0$
0%
#1153
#1154
1$
1%
#1155
1#
0$
#1156
0#
1$
#1157
1#
0%
#1158
0#
0$
#1159
1$
1%
#1160
1#
0$
#1161
1$
0%
#1162
0$
1%
#1163
#1164
0#
0%
#1165
#1166
#1167
1$
1%
#1168
0$
0%
#1169
1#
1%
#1170
1$
0%
#1171
#1172
0#
0$
#1173
1$
1%
#1174
#1175
0$
0%
#1176
1#
1%
#1177
#1178
0#
0%
#1179
1#
1$
#1180
0#
1%
#1181
1#
0%
#1182
0#
1%
#1183
0$
0%
#1184
1#
1$
#1185
#1186
0#
0$
#1187
1$
1%
#1188
#1189
0$
0%
#1190
#1191
1$
1%
#1192
#1193
#1194
1#
0%
#1195
0#
0$
#1196
1$
1%
#1197
1#
0$
#1198
1$
0%
#1199
0$
1%
#1200
0#
0%
#1201
1#
1$
#1202
0#
0$
#1203
#1204
1#
1%
#1205
0#
1$
#1206
#1207
#1208
0$
0%
#1209
#1210
1#
1%
#1211
0#
0%
#1212
1#
1$
#1213
0#
0$
#1214
1$
1%
#1215
1#
0$
#1216
#1217
1$
0%
#1218
0#
1%
#1219
1#
0%
#1220
0$
1%
#1221
0#
0%
#1222
1#
1$
#1223
#1224
#1225
#1226
#1227
0$
1%
#1228
0#
1$
#1229
1#
0$
#1230
#1231
#1232
0#
0%
#1233
1$
1%
#1234
#1235
#1236
1#
0%
#1237
0$
1%
#1238
0#
0%
#1239
1$
1%
#1240
1#
0%
#1241
0#
0$
#1242
1#
1$
#1243
#1244
0$
1%
#1245
0#
0%
#1246
1$
1%
#1247
0$
0%
#1248
1#
1%
#1249
1$
0%
#1250
0#
0$
#1251
1#
1$
#1252
0$
1%
#1253
0#
1$
#1254
1#
0$
#1255
0#
0%
#1256
1#
1$
#1257
0$
1%
#1258
0#
0%
#1259
1$
1%
#1260
0$
0%
#1261
1#
1%
#1262
#1263
0#
0%
#1264
#1265
#1266
1$
1%
#1267
#1268
1#
0$
#1269
0#
0%
#1270
#1271
1#
1$
#1272
0$
1%
#1273
0#
0%
#1274
#1275
1#
1%
#1276
0#
1$
#1277
#1278
1#
0$
#1279
1$
0%
#1280
0#
1%
#1281
0$
0%
#1282
#1283
1#
1%
#1284
0#
1$
#1285
0$
0%
#1286
1$
1%
#1287
1#
0%
#1288
#1289
#1290
#1291
#1292
0#
1%
#1293
#1294
0$
0%
#1295
#1296
1#
1%
#1297
#1298
0#
0%
#1299
#1300
#1301
#1302
#1303
1#
1$
#1304
#1305
#1306
0#
0$
#1307
#1308
1$
1%
#1309
1#
0$
#1310
1$
0%
#1311
0#
0$
#1312
1$
1%
#1313
0$
0%
#1314
#1315
1#
1%
#1316
1$
0%
#1317
0#
1%
#1318
1#
0%
#1319
0#
1%
#1320
#1321
0$
0%
#1322
#1323
#1324
1#
1$
#1325
0#
0$
#1326
1#
1%
#1327
1$
0%
#1328
0#
1%
#1329
1#
0$
#1330
0#
0%
#1331
1$
1%
#1332
0$
0%
#1333
1$
1%
#1334
1#
0$
#1335
0#
0%
#1336
#1337
#1338
1#
1$
#1339
0#
0$
#1340
#1341
1#
1$
#1342
0#
0$
#1343
#1344
1#
1%
#1345
0#
1$
#1346
0$
0%
#1347
#1348
#1349
#1350
1#
1%
#1351
0#
1$
#1352
1#
0$
#1353
#1354
1$
0%
#1355
0#
0$
#1356
1#
1$
#1357
#1358
0$
1%
#1359
0#
1$
#1360
0$
0%
#1361
#1362
1#
1$
#1363
#1364
#1365
0$
1%
#1366
1$
0%
#1367
0$
1%
#1368
0#
0%
#1369
1$
1%
#1370
1#
0%
#1371
0$
1%
#1372
0#
1$
#1373
0$
0%
#1374
1#
1%
#1375
1$
0%
#1376
0#
1%
#1377
1#
0%
#1378
0#
0$
#1379
1#
1%
#1380
#1381
0#
1$
#1382
0$
0%
#1383
1#
1%
#1384
0#
0%
#1385
1#
1%
#1386
1$
0%
#1387
0#
1%
#1388
0$
0%
#1389
1#
1$
#1390
0#
0$
#1391
1$
1%
#1392
#1393
0$
0%
#1394
1$
1%
#1395
#1396
#1397
0$
0%
#1398
1#
1%
#1399
0#
1$
#1400
#1401
1#
0%
#1402
0#
0$
#1403
#1404
#1405
1#
1$
#1406
0#
1%
#1407
0$
0%
#1408
1#
1%
#1409
1$
0%
#1410
0#
1%
#1411
0$
0%
#1412
1$
1%
#1413
#1414
1#
0$
#1415
1$
0%
#1416
0$
1%
#1417
0#
0%
#1418
#1419
1$
1%
#1420
0$
0%
#1421
1$
1%
#1422
1#
0$
#1423
#1424
0#
0%
#1425
1#
1%
#1426
0#
0%
#1427
#1428
1#
1%
#1429
0#
0%
#1430
1$
1%
#1431
1#
0$
#1432
1$
0%
#1433
0#
0$
#1434
1#
1%
#1435
#1436
0#
1$
#1437
1#
0$
#1438
#1439
0#
1$
#1440
1#
0$
#1441
0#
1$
#1442
0$
0%
#1443
1#
1$
#1444
#1445
#1446
0#
0$
#1447
1#
1%
#1448
1$
0%
#1449
0#
0$
#1450
1$
1%
#1451
0$
0%
#1452
1$
1%
#1453
#1454
#1455
#1456
1#
0$
#1457
0#
1$
#1458
1#
0%
#1459
0#
0$
#1460
1#
1$
#1461
#1462
#1463
0$
1%
#1464
0#
1$
#1465
0$
0%
#1466
1$
1%
#1467
1#
0$
#1468
0#
1$
#1469
1#
0$
#1470
0#
0%
#1471
1#
1$
#1472
0#
1%
#1473
#1474
1#
0$
#1475
#1476
1$
0%
#1477
0$
1%
#1478
0#
1$
#1479
0$
0%
#1480
1$
1%
#1481
1#
0%
#1482
0#
0$
#1483
1#
1%
#1484
1$
0%
#1485
0$
1%
#1486
#1487
1$
0%
#1488
0#
0$
#1489
1#
1$
#1490
0#
0$
#1491
1#
1%
#1492
#1493
0#
1$
#1494
1#
0%
#1495
0#
0$
#1496
1$
1%
#1497
1#
0$
#1498
#1499
0#
0%
#1500
1#
1$
#1501
0#
0$
#1502
#1503
#1504
1$
1%
#1505
1#
0$
#1506
#1507
0#
1$
#1508
#1509
0$
0%
#1510
#1511
#1512
1#
1$
#1513
0#
0$
#1514
1#
1%
#1515
1$
0%
#1516
0#
1%
#1517
1#
0$
#1518
1$
0%
#1519
0#
1%
#1520
#1521
0$
0%
#1522
1#
1%
#1523
1$
0%
#1524
#1525
#1526
0#
1%
#1527
1#
0%
#1528
0#
1%
#1529
0$
0%
#1530
1$
1%
#1531
1#
0$
#1532
0#
0%
#1533
#1534
#1535
1#
1%
#1536
1$
0%
#1537
0#
0$
#1538
1$
1%
#1539
1#
0%
#1540
#1541
#1542
0#
0$
#1543
1$
1%
#1544
0$
0%
#1545
1#
1%
#1546
#1547
0#
0%
#1548
#1549
#1550
1$
1%
#1551
1#
0%
#1552
#1553
#1554
0$
1%
#1555
0#
0%
#1556
1#
1$
#1557
0$
1%
#1558
0#
1$
#1559
1#
0$
#1560
0#
0%
#1561
1$
1%
#1562
0$
0%
#1563
1#
1%
#1564
0#
1$
#1565
1#
0$
#1566
#1567
#1568
#1569
#1570
0#
1$
#1571
0$
0%
#1572
1#
1$
#1573
0#
1%
#1574
1#
0%
#1575
#1576
#1577
0#
1%
#1578
1#
0$
#1579
1$
0%
#1580
0$
1%
#1581
#1582
0#
0%
#1583
#1584
1$
1%
#1585
0$
0%
#1586
1#
1$
#1587
0#
0$
#1588
#1589
1#
1$
#1590
0$
1%
#1591
0#
0%
#1592
1#
1$
#1593
0$
1%
#1594
1$
0%
#1595
0$
1%
#1596
#1597
#1598
0#
1$
#1599
0$
0%
#1600
1#
1%
#1601
0#
0%
#1602
1#
1$
#1603
0#
0$
#1604
1#
1$
#1605
#1606
0$
1%
#1607
#1608
1$
0%
#1609
0#
0$
#1610
1$
1%
#1611
#1612
1#
0%
#1613
#1614
#1615
0$
1%
#1616
0#
1$
#1617
#1618
0$
0%
#1619
1#
1%
#1620
1$
0%
#1621
0$
1%
#1622
#1623
0#
0%
#1624
1#
1%
#1625
0#
1$
#1626
1#
0$
#1627
#1628
0#
0%
#1629
1#
1$
#1630
0#
0$
#1631
1#
1%
#1632
1$
0%
#1633
0$
1%
#1634
1$
0%
#1635
0#
0$
#1636
1$
1%
#1637
#1638
1#
0$
#1639
1$
0%
#1640
0#
1%
#1641
#1642
1#
0%
#1643
#1644
0#
0$
#1645
#1646
1$
1%
#1647
#1648
#1649
1#
0%
#1650
0#
1%
#1651
1#
0$
#1652
0#
1$
#1653
1#
0$
#1654
#1655
1$
0%
#1656
#1657
0#
1%
#1658
1#
0%
#1659
0#
1%
#1660
1#
0%
#1661
#1662
0#
1%
#1663
1#
0%
#1664
0#
0$
#1665
1$
1%
#1666
0$
0%
#1667
1#
1%
#1668
1$
0%
#1669
0#
1%
#1670
1#
0%
#1671
0#
1%
#1672
1#
0%
#1673
0#
0$
#1674
#1675
1#
1%
#1676
#1677
#1678
#1679
1$
0%
#1680
#1681
0#
1%
#1682
1#
0$
#1683
1$
0%
#1684
0$
1%
#1685
0#
0%
#1686
1#
1%
#1687
#1688
1$
0%
#1689
0#
0$
#1690
1$
1%
#1691
#1692
1#
0%
#1693
0$
1%
#1694
0#
0%
#1695
1$
1%
#1696
0$
0%
#1697
1$
1%
#1698
#1699
#1700
1#
0$
#1701
0#
1$
#1702
1#
0%
#1703
0$
1%
#1704
#1705
0#
1$
#1706
1#
0$
#1707
0#
1$
#1708
0$
0%
#1709
1#
1%
#1710
0#
1$
#1711
1#
0$
#1712
0#
1$
#1713
0$
0%
#1714
#1715
#1716
1#
1%
#1717
#1718
#1719
0#
0%
#1720
1$
1%
#1721
1#
0$
#1722
#1723
1$
0%
#1724
0#
0$
#1725
1#
1%
#1726
0#
0%
#1727
1#
1%
#1728
1$
0%
#1729
0#
0$
#1730
1#
1%
#1731
0#
0%
#1732
1$
1%
#1733
0$
0%
#1734
1#
1$
#1735
0#
0$
#1736
#1737
1$
1%
#1738
#1739
1#
0$
#1740
#1741
0#
1$
#1742
1#
0%
#1743
0$
1%
#1744
0#
0%
#1745
#1746
#1747
1$
1%
#1748
1#
0%
#1749
#1750
0#
1%
#1751
1#
0$
#1752
1$
0%
#1753
#1754
0#
0$
#1755
1#
1$
#1756
0$
1%
#1757
#1758
#1759
0#
0%
#1760
1$
1%
#1761
#1762
1#
0$
#1763
0#
1$
#1764
1#
0%
#1765
0#
1%
#1766
#1767
1#
0$
#1768
0#
1$
#1769
1#
0$
#1770
1$
0%
#1771
0$
1%
#1772
#1773
0#
0%
#1774
1#
1$
#1775
0#
1%
#1776
0$
0%
#1777
1$
1%
#1778
1#
0$
#1779
0#
0%
#1780
1#
1%
#1781
0#
0%
#1782
1#
1$
#1783
0#
1%
#1784
#1785
1#
0$
#1786
0#
1$
#1787
#1788
1#
0%
#1789
0#
0$
#1790
#1791
#1792
1#
1%
#1793
#1794
#1795
0#
0%
#1796
#1797
#1798
#1799
1#
1%
#1800
0#
1$
#1801
0$
0%
#1802
1$
1%
#1803
#1804
0$
0%
#1805
#1806
#1807
1$
1%
#1808
#1809
1#
0%
#1810
0$
1%
#1811
0#
0%
#1812
#1813
#1814
1#
1$
#1815
#1816
0#
1%
#1817
1#
0$
#1818
0#
1$
#1819
0$
0%
#1820
1#
1%
#1821
0#
0%
#1822
#1823
1#
1%
#1824
0#
1$
#1825
#1826
1#
0$
#1827
1$
0%
#1828
0#
1%
#1829
#1830
1#
0%
#1831
0#
1%
#1832
0$
0%
#1833
1$
1%
#1834
1#
0$
#1835
1$
0%
#1836
0#
0$
#1837
1#
1%
#1838
0#
0%
#1839
#1840
1#
1%
#1841
0#
0%
#1842
1$
1%
#1843
#1844
1#
0$
#1845
0#
0%
#1846
1#
1$
#1847
#1848
#1849
0#
0$
#1850
1#
1%
#1851
1$
0%
#1852
0#
0$
#1853
1#
1%
