projects/ALU/vsrc/bcd8seg.v
`timescale 1ps/1ps

module bcd8seg(
  input  [3:0] b,
  output reg [7:0] h
);
// detailed implementation ...
    always @(*) begin
        case(b)
            4'b0000 : h=8'b0000_0011;//0
            4'b0001 : h=8'b1001_1111;//1
            4'b0010 : h=8'b0010_0101;//2
            4'b0011 : h=8'b0000_1101;//3
            4'b0100 : h=8'b1001_1001;//4
            4'b0101 : h=8'b0100_1001;//5
            4'b0110 : h=8'b0100_0001;//6
            4'b0111 : h=8'b0001_1111;//7
            4'b1000 : h=8'b0000_0001;//8
            4'b1001 : h=8'b0000_1001;//9
            default : h=8'b0001_0011;//error
        endcase
    end

endmodule
            // 4'b0000:h=7'b000000;
            // 4'b0001:h=7'b000000;
            // 4'b0010:h=7'b000000;
            // 4'b0011:h=7'b000000;
            // 4'b0100:h=7'b000000;//4
            // 4'b0101:h=7'b000000;
            // 4'b0110:h=7'b000000;
            // 4'b0111:h=7'b000000;
            // 4'b1001:h=7'b000000;//8
            // 4'b1010:h=7'b000000;//9
// assign segs[0] = 8'b11111101;
// assign segs[1] = 8'b01100000;
// assign segs[2] = 8'b11011010;
// assign segs[3] = 8'b11110010;
// assign segs[4] = 8'b01100110;
// assign segs[5] = 8'b10110110;
// assign segs[6] = 8'b10111110;
// assign segs[7] = 8'b11100000;

projects/ALU/vsrc/alu.v
`timescale 1ps/1ps
//有符号数的补码加法器
module alu #
(
    parameter N = 4
)
(
   input      [N-1:0]       a   ,
   input      [N-1:0]       b   ,
   input      [2:0]         sel  ,
   output                   carry,//进位
   output                   zero,//结果是否为0
   output                   overflow,//溢出
   output   reg  [N-1:0]    s  //输出指示数码管
);


    localparam  ADD = 3'b000,
                SUB = 3'b001,
                NOT = 3'b010,
                AND = 3'b011,
                OR  = 3'b100,
                XOR = 3'b101,
                CMP = 3'b110,
                EQU = 3'b111;

    wire [2:0]   flag_add;  //internal add/sub flag signal
    wire [N-1:0] s_add;     //internal add/sub result signal
    wire [2:0]   flag_logic;//internal logic flag signal
    wire [N-1:0] s_logic;   //internal logic  result signal

    wire [N-1:0] s_not;//internal not result signal
    wire [N-1:0] s_and;//internal and result signal
    wire [N-1:0] s_or;//internal or  result signal
    wire [N-1:0] s_xor;//internal xor result signal
    wire [N-1:0] s_cmp;//internal cmp result signal
    wire [N-1:0] s_equ;//internal equ result signal

    //mux 
    always @(*) begin
        case (sel)
            ADD:t_adder(a,b,0,carry,zero,overflow,s);
            SUB:t_adder(a,b,1,carry,zero,overflow,s); 
            NOT:t_not(a,carry,zero,overflow,s);
            AND:t_and(a,b,carry,zero,overflow,s);
            OR :t_or (a,b,carry,zero,overflow,s);
            XOR:t_xor(a,b,carry,zero,overflow,s);
            CMP:t_cmp(a,b,carry,zero,overflow,s);
            EQU:t_equ(a,b,carry,zero,overflow,s);
            default:s={N{1'b1}};
        endcase
    end

//ADD or SUB instructions
task t_adder;
input      [N-1:0]      a        ;
input      [N-1:0]      b        ;
input                  add_sub  ;//0-add 1-sub

output                 carry    ;//进位
output                 zero     ;//结果是否为0
output                 overflow ;//溢出
output     [N-1:0]     s        ;

begin
    //减数计算
    reg [N-1:0] t_as;
    reg carry_f;
    t_as = { {N{add_sub}} ^ b } + //与add_sub异或，0为加法b不变，1为减法b取反
                            {{(N-1){1'b0}} , add_sub};//b反+1变补码
    {carry,s} =  a + t_as ;
    //carry = 1;//carry_f ^ add_sub;//carry的减法错位
    //溢出逻辑
    overflow = ((a[N-1]==t_as[N-1])&&(s[N-1]!=a[N-1]));
    //全0逻辑
    zero = ~(|s);
end
endtask

//NOT instructions
task t_not;
input      [N-1:0]      a        ;
output                 carry    ;//进位
output                 zero     ;//结果是否为0
output                 overflow ;//溢出
output     [N-1:0]     s        ;
begin
    s=~a;
    carry=0;
    zero=0;
    overflow=0;
end
endtask

//AND instructions
task t_and;
input      [N-1:0]      a        ;
input      [N-1:0]      b        ;
output                 carry    ;//进位
output                 zero     ;//结果是否为0
output                 overflow ;//溢出
output     [N-1:0]     s        ;
begin
    s=a&b;
    carry=0;
    zero=0;
    overflow=0;
end
endtask

//OR instructions
task t_or;
input      [N-1:0]      a        ;
input      [N-1:0]      b        ;
output                 carry    ;//进位
output                 zero     ;//结果是否为0
output                 overflow ;//溢出
output     [N-1:0]     s        ;
begin
    s=a|b;
    carry=0;
    zero=0;
    overflow=0;
end
endtask

//XOR instructions
task t_xor;
input      [N-1:0]      a        ;
input      [N-1:0]      b        ;
output                 carry    ;//进位
output                 zero     ;//结果是否为0
output                 overflow ;//溢出
output     [N-1:0]     s        ;
begin
    s=a^b;
    carry=0;
    zero=0;
    overflow=0;
end
endtask

//CMP (a less than b) instructions
//适用于有符号数,无符号数使用进位和加减符进行比较
task t_cmp;
input      [N-1:0]      a        ;
input      [N-1:0]      b        ;
output                 carry    ;//进位
output                 zero     ;//结果是否为0
output                 overflow ;//溢出
output     [N-1:0]     s        ;
begin
    t_adder(.a(a), .b(b), .add_sub(1'b1), .carry(carry), 
            .zero(zero), .overflow(overflow), .s(s) );
    s = {N{s[N-1]^overflow}};
end
endtask

//EQU instructions
task t_equ;
input      [N-1:0]       a        ;
input      [N-1:0]       b        ;
output                 carry    ;//进位
output                 zero     ;//结果是否为0
output                 overflow ;//溢出
output     [N-1:0]     s        ;
begin
    t_adder(.a(a), .b(b), .add_sub(1'b1), .carry(carry), 
            .zero(zero), .overflow(overflow), .s(s) );
    s = {N{zero}};
end
endtask


endmodule





    // wire s_add_sub;//internal add sub flag signal
    // assign s_add_sub=(sel==SUB);//加0减1
    // adder #(N) i_add(a,b,s_add_sub,carry,zero,overflow,s_add);
    //logic

projects/muler/vsrc/comp2source.v
`timescale 1ps/1ps    
// warning n should > 2
// 补转回源码就是再进行一次补码转换即可
module comp2source
#(
    parameter N = 4
)
(
   input      [N-1:0]       a,
   output     [N-1:0]       a_comp   
);

    assign a_comp = a[N-1] ? 
            { a[N-1] , ~a[N-2:0] + 1'b1 } : a;
//逻辑不太复杂时，用位拼接，二选一
endmodule

projects/muler/vsrc/source2comp.v
`timescale 1ps/1ps    
// warning n should > 2
module source2comp
#(
    parameter N = 4
)
(
   input      [N-1:0]       a,
   output     [N-1:0]       a_comp   
);
 
    assign a_comp = a[N-1] ? 
            { a[N-1] , ~a[N-2:0] + 1'b1 } : a;
//逻辑不太复杂时，用位拼接，二选一
endmodule

projects/ALU/vsrc/top.v
`timescale 1ps/1ps
//*****WARNING******
//****发现重要BUG-1****
//NVBROAD输出信号不能与$display冲突
//并且通过间接信号进行assign也没用也没用
//否则导致$display没有数据
//****发现重要BUG-2****
//for内部不能进行赋值，否则无结果
//你需要另外开一个initial进行赋值

module top(
   input      [3:0]       a   ,
   input      [3:0]       b   ,
   input      [2:0]       sel  ,
   
   output                  carry,
   output                  zero,
   output                  overflow,
   output     [3:0]        s,
   output     [15:0]       led_o,
   output     [15:0]       hex_o  //输出指示数码管
);

   wire [3:0] a_comp,b_comp;
   source2comp i_a (a,a_comp);
   comp2source i_b (b,b_comp);
   


   alu #(4) i_alu
   (
   .b       (b) ,
   .a       (a) ,
   .sel     (sel) ,
   .carry   (carry),//进位
   .zero    (zero),//结果是否为0
   .overflow(overflow),//溢出
   .s       (s) //输出指示数码管
   );
   //board debug interface
   bcd8seg ia( .b(a), .h(hex_o[15:8]) );//output a to hex0
   bcd8seg ib( .b(b), .h(hex_o[7:0]) );//output b to hex0
   assign led_o[3:0] = s;
   assign led_o[15:13]={carry,zero,overflow};


endmodule






   // initial for(integer i=0;i<8;i++) $display("top:%d %d %d ",a,b,s);

   // alu_tb#(4) i_tb
   // (
   // .b_o       (b) ,
   // .a_o       (a) ,
   // .sel_o     (sel) ,
   // .carry   (carry),//进位
   // .zero    (zero),//结果是否为0
   // .overflow(overflow),//溢出
   // .s       (s) //输出指示数码管
   // );

projects/ALU/vlt_dump.vcd
$version Generated by VerilatedVcd $end
$date Mon Apr 11 17:10:48 2022 $end
$timescale 1ns $end

 $scope module TOP $end
  $var wire  4 # a [3:0] $end
  $var wire  4 $ b [3:0] $end
  $var wire  1 & carry $end
  $var wire 16 + hex_o [15:0] $end
  $var wire 16 * led_o [15:0] $end
  $var wire  1 ( overflow $end
  $var wire  4 ) s [3:0] $end
  $var wire  3 % sel [2:0] $end
  $var wire  1 ' zero $end
  $scope module top $end
   $var wire  4 # a [3:0] $end
   $var wire  4 , a_comp [3:0] $end
   $var wire  4 $ b [3:0] $end
   $var wire  4 - b_comp [3:0] $end
   $var wire  1 & carry $end
   $var wire 16 + hex_o [15:0] $end
   $var wire 16 * led_o [15:0] $end
   $var wire  1 ( overflow $end
   $var wire  4 ) s [3:0] $end
   $var wire  3 % sel [2:0] $end
   $var wire  1 ' zero $end
   $scope module i_a $end
    $var wire 32 0 N [31:0] $end
    $var wire  4 # a [3:0] $end
    $var wire  4 , a_comp [3:0] $end
   $upscope $end
   $scope module i_alu $end
    $var wire  3 1 ADD [2:0] $end
    $var wire  3 4 AND [2:0] $end
    $var wire  3 7 CMP [2:0] $end
    $var wire  3 8 EQU [2:0] $end
    $var wire 32 0 N [31:0] $end
    $var wire  3 3 NOT [2:0] $end
    $var wire  3 5 OR [2:0] $end
    $var wire  3 2 SUB [2:0] $end
    $var wire  3 6 XOR [2:0] $end
    $var wire  4 # a [3:0] $end
    $var wire  4 $ b [3:0] $end
    $var wire  1 & carry $end
    $var wire  3 9 flag_add [2:0] $end
    $var wire  3 ; flag_logic [2:0] $end
    $var wire  1 ( overflow $end
    $var wire  4 ) s [3:0] $end
    $var wire  4 : s_add [3:0] $end
    $var wire  4 > s_and [3:0] $end
    $var wire  4 A s_cmp [3:0] $end
    $var wire  4 B s_equ [3:0] $end
    $var wire  4 < s_logic [3:0] $end
    $var wire  4 = s_not [3:0] $end
    $var wire  4 ? s_or [3:0] $end
    $var wire  4 @ s_xor [3:0] $end
    $var wire  3 % sel [2:0] $end
    $var wire  1 ' zero $end
   $upscope $end
   $scope module i_b $end
    $var wire 32 0 N [31:0] $end
    $var wire  4 $ a [3:0] $end
    $var wire  4 - a_comp [3:0] $end
   $upscope $end
   $scope module ia $end
    $var wire  4 # b [3:0] $end
    $var wire  8 . h [7:0] $end
   $upscope $end
   $scope module ib $end
    $var wire  4 $ b [3:0] $end
    $var wire  8 / h [7:0] $end
   $upscope $end
  $upscope $end
 $upscope $end
$enddefinitions $end


#1
b1000 #
b1000 $
b000 %
1&
1'
1(
b0000 )
b1110000000000000 *
b0111100001111000 +
b1000 ,
b1000 -
b01111000 .
b01111000 /
b00000000000000000000000000000100 0
b000 1
b001 2
b010 3
b011 4
b100 5
b101 6
b110 7
b111 8
b000 9
b0000 :
b000 ;
b0000 <
b0000 =
b0000 >
b0000 ?
b0000 @
b0000 A
b0000 B
#2
b1001 $
0'
b0001 )
b1010000000000001 *
b0111100000101101 +
b1111 -
b00101101 /
#3
b1010 $
b0010 )
b1010000000000010 *
b0111100001110111 +
b1110 -
b01110111 /
#4
b1011 $
b0011 )
b1010000000000011 *
b0111100001101111 +
b1101 -
b01101111 /
#5
b1100 $
b0100 )
b1010000000000100 *
b0111100001110010 +
b1100 -
b01110010 /
#6
b1101 $
b0101 )
b1010000000000101 *
b0111100001101011 +
b1011 -
b01101011 /
#7
b1110 $
b0110 )
b1010000000000110 *
b0111100001100010 +
b1010 -
b01100010 /
#8
b1111 $
b0111 )
b1010000000000111 *
b0111100001100101 +
b1001 -
b01100101 /
#9
b0000 $
0(
b1000 )
b1000000000001000 *
b0111100000000011 +
b0000 -
b00000011 /
#10
b0001 $
b1001 )
b1000000000001001 *
b0111100010011111 +
b0001 -
b10011111 /
#11
b0010 $
b1010 )
b1000000000001010 *
b0111100000100101 +
b0010 -
b00100101 /
#12
b0011 $
b1011 )
b1000000000001011 *
b0111100000001101 +
b0011 -
b00001101 /
#13
b0100 $
b1100 )
b1000000000001100 *
b0111100010011001 +
b0100 -
b10011001 /
#14
b0101 $
b1101 )
b1000000000001101 *
b0111100001001001 +
b0101 -
b01001001 /
#15
b0110 $
b1110 )
b1000000000001110 *
b0111100001000001 +
b0110 -
b01000001 /
#16
b0111 $
b1111 )
b1000000000001111 *
b0111100000011111 +
b0111 -
b00011111 /
#17
b1001 #
b1000 $
1(
b0001 )
b1010000000000001 *
b0010110101111000 +
b1111 ,
b1000 -
b00101101 .
b01111000 /
#18
b1001 $
b0010 )
b1010000000000010 *
b0010110100101101 +
b1111 -
b00101101 /
#19
b1010 $
b0011 )
b1010000000000011 *
b0010110101110111 +
b1110 -
b01110111 /
#20
b1011 $
b0100 )
b1010000000000100 *
b0010110101101111 +
b1101 -
b01101111 /
#21
b1100 $
b0101 )
b1010000000000101 *
b0010110101110010 +
b1100 -
b01110010 /
#22
b1101 $
b0110 )
b1010000000000110 *
b0010110101101011 +
b1011 -
b01101011 /
#23
b1110 $
b0111 )
b1010000000000111 *
b0010110101100010 +
b1010 -
b01100010 /
#24
b1111 $
0(
b1000 )
b1000000000001000 *
b0010110101100101 +
b1001 -
b01100101 /
#25
b0000 $
b1001 )
b1000000000001001 *
b0010110100000011 +
b0000 -
b00000011 /
#26
b0001 $
b1010 )
b1000000000001010 *
b0010110110011111 +
b0001 -
b10011111 /
#27
b0010 $
b1011 )
b1000000000001011 *
b0010110100100101 +
b0010 -
b00100101 /
#28
b0011 $
b1100 )
b1000000000001100 *
b0010110100001101 +
b0011 -
b00001101 /
#29
b0100 $
b1101 )
b1000000000001101 *
b0010110110011001 +
b0100 -
b10011001 /
#30
b0101 $
b1110 )
b1000000000001110 *
b0010110101001001 +
b0101 -
b01001001 /
#31
b0110 $
b1111 )
b1000000000001111 *
b0010110101000001 +
b0110 -
b01000001 /
#32
b0111 $
0&
1'
b0000 )
b0100000000000000 *
b0010110100011111 +
b0111 -
b00011111 /
#33
b1010 #
b1000 $
1&
0'
1(
b0010 )
b1010000000000010 *
b0111011101111000 +
b1110 ,
b1000 -
b01110111 .
b01111000 /
#34
b1001 $
b0011 )
b1010000000000011 *
b0111011100101101 +
b1111 -
b00101101 /
#35
b1010 $
b0100 )
b1010000000000100 *
b0111011101110111 +
b1110 -
b01110111 /
#36
b1011 $
b0101 )
b1010000000000101 *
b0111011101101111 +
b1101 -
b01101111 /
#37
b1100 $
b0110 )
b1010000000000110 *
b0111011101110010 +
b1100 -
b01110010 /
#38
b1101 $
b0111 )
b1010000000000111 *
b0111011101101011 +
b1011 -
b01101011 /
#39
b1110 $
0(
b1000 )
b1000000000001000 *
b0111011101100010 +
b1010 -
b01100010 /
#40
b1111 $
b1001 )
b1000000000001001 *
b0111011101100101 +
b1001 -
b01100101 /
#41
b0000 $
b1010 )
b1000000000001010 *
b0111011100000011 +
b0000 -
b00000011 /
#42
b0001 $
b1011 )
b1000000000001011 *
b0111011110011111 +
b0001 -
b10011111 /
#43
b0010 $
b1100 )
b1000000000001100 *
b0111011100100101 +
b0010 -
b00100101 /
#44
b0011 $
b1101 )
b1000000000001101 *
b0111011100001101 +
b0011 -
b00001101 /
#45
b0100 $
b1110 )
b1000000000001110 *
b0111011110011001 +
b0100 -
b10011001 /
#46
b0101 $
b1111 )
b1000000000001111 *
b0111011101001001 +
b0101 -
b01001001 /
#47
b0110 $
0&
1'
b0000 )
b0100000000000000 *
b0111011101000001 +
b0110 -
b01000001 /
#48
b0111 $
0'
b0001 )
b0000000000000001 *
b0111011100011111 +
b0111 -
b00011111 /
#49
b1011 #
b1000 $
1&
1(
b0011 )
b1010000000000011 *
b0110111101111000 +
b1101 ,
b1000 -
b01101111 .
b01111000 /
#50
b1001 $
b0100 )
b1010000000000100 *
b0110111100101101 +
b1111 -
b00101101 /
#51
b1010 $
b0101 )
b1010000000000101 *
b0110111101110111 +
b1110 -
b01110111 /
#52
b1011 $
b0110 )
b1010000000000110 *
b0110111101101111 +
b1101 -
b01101111 /
#53
b1100 $
b0111 )
b1010000000000111 *
b0110111101110010 +
b1100 -
b01110010 /
#54
b1101 $
0(
b1000 )
b1000000000001000 *
b0110111101101011 +
b1011 -
b01101011 /
#55
b1110 $
b1001 )
b1000000000001001 *
b0110111101100010 +
b1010 -
b01100010 /
#56
b1111 $
b1010 )
b1000000000001010 *
b0110111101100101 +
b1001 -
b01100101 /
#57
b0000 $
b1011 )
b1000000000001011 *
b0110111100000011 +
b0000 -
b00000011 /
#58
b0001 $
b1100 )
b1000000000001100 *
b0110111110011111 +
b0001 -
b10011111 /
#59
b0010 $
b1101 )
b1000000000001101 *
b0110111100100101 +
b0010 -
b00100101 /
#60
b0011 $
b1110 )
b1000000000001110 *
b0110111100001101 +
b0011 -
b00001101 /
#61
b0100 $
b1111 )
b1000000000001111 *
b0110111110011001 +
b0100 -
b10011001 /
#62
b0101 $
0&
1'
b0000 )
b0100000000000000 *
b0110111101001001 +
b0101 -
b01001001 /
#63
b0110 $
0'
b0001 )
b0000000000000001 *
b0110111101000001 +
b0110 -
b01000001 /
#64
b0111 $
b0010 )
b0000000000000010 *
b0110111100011111 +
b0111 -
b00011111 /
#65
b1100 #
b1000 $
1&
1(
b0100 )
b1010000000000100 *
b0111001001111000 +
b1100 ,
b1000 -
b01110010 .
b01111000 /
#66
b1001 $
b0101 )
b1010000000000101 *
b0111001000101101 +
b1111 -
b00101101 /
#67
b1010 $
b0110 )
b1010000000000110 *
b0111001001110111 +
b1110 -
b01110111 /
#68
b1011 $
b0111 )
b1010000000000111 *
b0111001001101111 +
b1101 -
b01101111 /
#69
b1100 $
0(
b1000 )
b1000000000001000 *
b0111001001110010 +
b1100 -
b01110010 /
#70
b1101 $
b1001 )
b1000000000001001 *
b0111001001101011 +
b1011 -
b01101011 /
#71
b1110 $
b1010 )
b1000000000001010 *
b0111001001100010 +
b1010 -
b01100010 /
#72
b1111 $
b1011 )
b1000000000001011 *
b0111001001100101 +
b1001 -
b01100101 /
#73
b0000 $
b1100 )
b1000000000001100 *
b0111001000000011 +
b0000 -
b00000011 /
#74
b0001 $
b1101 )
b1000000000001101 *
b0111001010011111 +
b0001 -
b10011111 /
#75
b0010 $
b1110 )
b1000000000001110 *
b0111001000100101 +
b0010 -
b00100101 /
#76
b0011 $
b1111 )
b1000000000001111 *
b0111001000001101 +
b0011 -
b00001101 /
#77
b0100 $
0&
1'
b0000 )
b0100000000000000 *
b0111001010011001 +
b0100 -
b10011001 /
#78
b0101 $
0'
b0001 )
b0000000000000001 *
b0111001001001001 +
b0101 -
b01001001 /
#79
b0110 $
b0010 )
b0000000000000010 *
b0111001001000001 +
b0110 -
b01000001 /
#80
b0111 $
b0011 )
b0000000000000011 *
b0111001000011111 +
b0111 -
b00011111 /
#81
b1101 #
b1000 $
1&
1(
b0101 )
b1010000000000101 *
b0110101101111000 +
b1011 ,
b1000 -
b01101011 .
b01111000 /
#82
b1001 $
b0110 )
b1010000000000110 *
b0110101100101101 +
b1111 -
b00101101 /
#83
b1010 $
b0111 )
b1010000000000111 *
b0110101101110111 +
b1110 -
b01110111 /
#84
b1011 $
0(
b1000 )
b1000000000001000 *
b0110101101101111 +
b1101 -
b01101111 /
#85
b1100 $
b1001 )
b1000000000001001 *
b0110101101110010 +
b1100 -
b01110010 /
#86
b1101 $
b1010 )
b1000000000001010 *
b0110101101101011 +
b1011 -
b01101011 /
#87
b1110 $
b1011 )
b1000000000001011 *
b0110101101100010 +
b1010 -
b01100010 /
#88
b1111 $
b1100 )
b1000000000001100 *
b0110101101100101 +
b1001 -
b01100101 /
#89
b0000 $
b1101 )
b1000000000001101 *
b0110101100000011 +
b0000 -
b00000011 /
#90
b0001 $
b1110 )
b1000000000001110 *
b0110101110011111 +
b0001 -
b10011111 /
#91
b0010 $
b1111 )
b1000000000001111 *
b0110101100100101 +
b0010 -
b00100101 /
#92
b0011 $
0&
1'
b0000 )
b0100000000000000 *
b0110101100001101 +
b0011 -
b00001101 /
#93
b0100 $
0'
b0001 )
b0000000000000001 *
b0110101110011001 +
b0100 -
b10011001 /
#94
b0101 $
b0010 )
b0000000000000010 *
b0110101101001001 +
b0101 -
b01001001 /
#95
b0110 $
b0011 )
b0000000000000011 *
b0110101101000001 +
b0110 -
b01000001 /
#96
b0111 $
b0100 )
b0000000000000100 *
b0110101100011111 +
b0111 -
b00011111 /
#97
b1110 #
b1000 $
1&
1(
b0110 )
b1010000000000110 *
b0110001001111000 +
b1010 ,
b1000 -
b01100010 .
b01111000 /
#98
b1001 $
b0111 )
b1010000000000111 *
b0110001000101101 +
b1111 -
b00101101 /
#99
b1010 $
0(
b1000 )
b1000000000001000 *
b0110001001110111 +
b1110 -
b01110111 /
#100
b1011 $
b1001 )
b1000000000001001 *
b0110001001101111 +
b1101 -
b01101111 /
#101
b1100 $
b1010 )
b1000000000001010 *
b0110001001110010 +
b1100 -
b01110010 /
#102
b1101 $
b1011 )
b1000000000001011 *
b0110001001101011 +
b1011 -
b01101011 /
#103
b1110 $
b1100 )
b1000000000001100 *
b0110001001100010 +
b1010 -
b01100010 /
#104
b1111 $
b1101 )
b1000000000001101 *
b0110001001100101 +
b1001 -
b01100101 /
#105
b0000 $
b1110 )
b1000000000001110 *
b0110001000000011 +
b0000 -
b00000011 /
#106
b0001 $
b1111 )
b1000000000001111 *
b0110001010011111 +
b0001 -
b10011111 /
#107
b0010 $
0&
1'
b0000 )
b0100000000000000 *
b0110001000100101 +
b0010 -
b00100101 /
#108
b0011 $
0'
b0001 )
b0000000000000001 *
b0110001000001101 +
b0011 -
b00001101 /
#109
b0100 $
b0010 )
b0000000000000010 *
b0110001010011001 +
b0100 -
b10011001 /
#110
b0101 $
b0011 )
b0000000000000011 *
b0110001001001001 +
b0101 -
b01001001 /
#111
b0110 $
b0100 )
b0000000000000100 *
b0110001001000001 +
b0110 -
b01000001 /
#112
b0111 $
b0101 )
b0000000000000101 *
b0110001000011111 +
b0111 -
b00011111 /
#113
b1111 #
b1000 $
1&
1(
b0111 )
b1010000000000111 *
b0110010101111000 +
b1001 ,
b1000 -
b01100101 .
b01111000 /
#114
b1001 $
0(
b1000 )
b1000000000001000 *
b0110010100101101 +
b1111 -
b00101101 /
#115
b1010 $
b1001 )
b1000000000001001 *
b0110010101110111 +
b1110 -
b01110111 /
#116
b1011 $
b1010 )
b1000000000001010 *
b0110010101101111 +
b1101 -
b01101111 /
#117
b1100 $
b1011 )
b1000000000001011 *
b0110010101110010 +
b1100 -
b01110010 /
#118
b1101 $
b1100 )
b1000000000001100 *
b0110010101101011 +
b1011 -
b01101011 /
#119
b1110 $
b1101 )
b1000000000001101 *
b0110010101100010 +
b1010 -
b01100010 /
#120
b1111 $
b1110 )
b1000000000001110 *
b0110010101100101 +
b1001 -
b01100101 /
#121
b0000 $
b1111 )
b1000000000001111 *
b0110010100000011 +
b0000 -
b00000011 /
#122
b0001 $
0&
1'
b0000 )
b0100000000000000 *
b0110010110011111 +
b0001 -
b10011111 /
#123
b0010 $
0'
b0001 )
b0000000000000001 *
b0110010100100101 +
b0010 -
b00100101 /
#124
b0011 $
b0010 )
b0000000000000010 *
b0110010100001101 +
b0011 -
b00001101 /
#125
b0100 $
b0011 )
b0000000000000011 *
b0110010110011001 +
b0100 -
b10011001 /
#126
b0101 $
b0100 )
b0000000000000100 *
b0110010101001001 +
b0101 -
b01001001 /
#127
b0110 $
b0101 )
b0000000000000101 *
b0110010101000001 +
b0110 -
b01000001 /
#128
b0111 $
b0110 )
b0000000000000110 *
b0110010100011111 +
b0111 -
b00011111 /
#129
b0000 #
b1000 $
1&
b1000 )
b1000000000001000 *
b0000001101111000 +
b0000 ,
b1000 -
b00000011 .
b01111000 /
#130
b1001 $
b1001 )
b1000000000001001 *
b0000001100101101 +
b1111 -
b00101101 /
#131
b1010 $
b1010 )
b1000000000001010 *
b0000001101110111 +
b1110 -
b01110111 /
#132
b1011 $
b1011 )
b1000000000001011 *
b0000001101101111 +
b1101 -
b01101111 /
#133
b1100 $
b1100 )
b1000000000001100 *
b0000001101110010 +
b1100 -
b01110010 /
#134
b1101 $
b1101 )
b1000000000001101 *
b0000001101101011 +
b1011 -
b01101011 /
#135
b1110 $
b1110 )
b1000000000001110 *
b0000001101100010 +
b1010 -
b01100010 /
#136
b1111 $
b1111 )
b1000000000001111 *
b0000001101100101 +
b1001 -
b01100101 /
#137
b0000 $
0&
1'
b0000 )
b0100000000000000 *
b0000001100000011 +
b0000 -
b00000011 /
#138
b0001 $
0'
b0001 )
b0000000000000001 *
b0000001110011111 +
b0001 -
b10011111 /
#139
b0010 $
b0010 )
b0000000000000010 *
b0000001100100101 +
b0010 -
b00100101 /
#140
b0011 $
b0011 )
b0000000000000011 *
b0000001100001101 +
b0011 -
b00001101 /
#141
b0100 $
b0100 )
b0000000000000100 *
b0000001110011001 +
b0100 -
b10011001 /
#142
b0101 $
b0101 )
b0000000000000101 *
b0000001101001001 +
b0101 -
b01001001 /
#143
b0110 $
b0110 )
b0000000000000110 *
b0000001101000001 +
b0110 -
b01000001 /
#144
b0111 $
b0111 )
b0000000000000111 *
b0000001100011111 +
b0111 -
b00011111 /
#145
b0001 #
b1000 $
1&
b1001 )
b1000000000001001 *
b1001111101111000 +
b0001 ,
b1000 -
b10011111 .
b01111000 /
#146
b1001 $
b1010 )
b1000000000001010 *
b1001111100101101 +
b1111 -
b00101101 /
#147
b1010 $
b1011 )
b1000000000001011 *
b1001111101110111 +
b1110 -
b01110111 /
#148
b1011 $
b1100 )
b1000000000001100 *
b1001111101101111 +
b1101 -
b01101111 /
#149
b1100 $
b1101 )
b1000000000001101 *
b1001111101110010 +
b1100 -
b01110010 /
#150
b1101 $
b1110 )
b1000000000001110 *
b1001111101101011 +
b1011 -
b01101011 /
#151
b1110 $
b1111 )
b1000000000001111 *
b1001111101100010 +
b1010 -
b01100010 /
#152
b1111 $
0&
1'
b0000 )
b0100000000000000 *
b1001111101100101 +
b1001 -
b01100101 /
#153
b0000 $
0'
b0001 )
b0000000000000001 *
b1001111100000011 +
b0000 -
b00000011 /
#154
b0001 $
b0010 )
b0000000000000010 *
b1001111110011111 +
b0001 -
b10011111 /
#155
b0010 $
b0011 )
b0000000000000011 *
b1001111100100101 +
b0010 -
b00100101 /
#156
b0011 $
b0100 )
b0000000000000100 *
b1001111100001101 +
b0011 -
b00001101 /
#157
b0100 $
b0101 )
b0000000000000101 *
b1001111110011001 +
b0100 -
b10011001 /
#158
b0101 $
b0110 )
b0000000000000110 *
b1001111101001001 +
b0101 -
b01001001 /
#159
b0110 $
b0111 )
b0000000000000111 *
b1001111101000001 +
b0110 -
b01000001 /
#160
b0111 $
1(
b1000 )
b0010000000001000 *
b1001111100011111 +
b0111 -
b00011111 /
#161
b0010 #
b1000 $
1&
0(
b1010 )
b1000000000001010 *
b0010010101111000 +
b0010 ,
b1000 -
b00100101 .
b01111000 /
#162
b1001 $
b1011 )
b1000000000001011 *
b0010010100101101 +
b1111 -
b00101101 /
#163
b1010 $
b1100 )
b1000000000001100 *
b0010010101110111 +
b1110 -
b01110111 /
#164
b1011 $
b1101 )
b1000000000001101 *
b0010010101101111 +
b1101 -
b01101111 /
#165
b1100 $
b1110 )
b1000000000001110 *
b0010010101110010 +
b1100 -
b01110010 /
#166
b1101 $
b1111 )
b1000000000001111 *
b0010010101101011 +
b1011 -
b01101011 /
#167
b1110 $
0&
1'
b0000 )
b0100000000000000 *
b0010010101100010 +
b1010 -
b01100010 /
#168
b1111 $
0'
b0001 )
b0000000000000001 *
b0010010101100101 +
b1001 -
b01100101 /
#169
b0000 $
b0010 )
b0000000000000010 *
b0010010100000011 +
b0000 -
b00000011 /
#170
b0001 $
b0011 )
b0000000000000011 *
b0010010110011111 +
b0001 -
b10011111 /
#171
b0010 $
b0100 )
b0000000000000100 *
b0010010100100101 +
b0010 -
b00100101 /
#172
b0011 $
b0101 )
b0000000000000101 *
b0010010100001101 +
b0011 -
b00001101 /
#173
b0100 $
b0110 )
b0000000000000110 *
b0010010110011001 +
b0100 -
b10011001 /
#174
b0101 $
b0111 )
b0000000000000111 *
b0010010101001001 +
b0101 -
b01001001 /
#175
b0110 $
1(
b1000 )
b0010000000001000 *
b0010010101000001 +
b0110 -
b01000001 /
#176
b0111 $
b1001 )
b0010000000001001 *
b0010010100011111 +
b0111 -
b00011111 /
#177
b0011 #
b1000 $
1&
0(
b1011 )
b1000000000001011 *
b0000110101111000 +
b0011 ,
b1000 -
b00001101 .
b01111000 /
#178
b1001 $
b1100 )
b1000000000001100 *
b0000110100101101 +
b1111 -
b00101101 /
#179
b1010 $
b1101 )
b1000000000001101 *
b0000110101110111 +
b1110 -
b01110111 /
#180
b1011 $
b1110 )
b1000000000001110 *
b0000110101101111 +
b1101 -
b01101111 /
#181
b1100 $
b1111 )
b1000000000001111 *
b0000110101110010 +
b1100 -
b01110010 /
#182
b1101 $
0&
1'
b0000 )
b0100000000000000 *
b0000110101101011 +
b1011 -
b01101011 /
#183
b1110 $
0'
b0001 )
b0000000000000001 *
b0000110101100010 +
b1010 -
b01100010 /
#184
b1111 $
b0010 )
b0000000000000010 *
b0000110101100101 +
b1001 -
b01100101 /
#185
b0000 $
b0011 )
b0000000000000011 *
b0000110100000011 +
b0000 -
b00000011 /
#186
b0001 $
b0100 )
b0000000000000100 *
b0000110110011111 +
b0001 -
b10011111 /
#187
b0010 $
b0101 )
b0000000000000101 *
b0000110100100101 +
b0010 -
b00100101 /
#188
b0011 $
b0110 )
b0000000000000110 *
b0000110100001101 +
b0011 -
b00001101 /
#189
b0100 $
b0111 )
b0000000000000111 *
b0000110110011001 +
b0100 -
b10011001 /
#190
b0101 $
1(
b1000 )
b0010000000001000 *
b0000110101001001 +
b0101 -
b01001001 /
#191
b0110 $
b1001 )
b0010000000001001 *
b0000110101000001 +
b0110 -
b01000001 /
