projects/shifter/random_seq_gen/vsrc/shifter.v
`timescale 1ps/1ps
//4-bits shifter
module shifter #
(
    parameter N = 8
)
(
   input        In,
   input        Clk,
   input        L_R,//0算术移位,1逻辑意味

   output reg [N-1:0]     Q
);

    always@(posedge Clk)begin
        //L_R=1左移(both a_l),L_R=0右移
        Q = L_R ?{Q[N-2:0],In}:{In,Q[N-1:1]};
    end

endmodule

projects/shifter/random_seq_gen/vsrc/top.v
`timescale 1ps/1ps
//*****WARNING******
//****发现重要BUG-1****
//NVBROAD输出信号不能与$display冲突
//并且通过间接信号进行assign也没用也没用
//否则导致$display没有数据
//****发现重要BUG-2****
//for内部不能进行赋值，否则无结果
//你需要另外开一个initial进行赋值

module top(
   input                   Clk    ,
   output     [7:0]        Q      ,
   output                  Dout   ,
   output     [15:0]       led_o  ,
   output     [15:0]       hex_o  //输出指示数码管
);

   //random Din logic
   wire In_1,In_2;
   assign In_1 = Q[0]^Q[2]^Q[3]^Q[4];
   assign In_2 = (Q==8'b0000_0000) ? 1: In_1;//全0序列时插入1,防止卡卡死

   //design module instance 
   shifter i_shifter
   (
      In_2   ,
      Clk     ,
      1'b0    ,//L_R=1左移(both a_l),L_R=0右移
      Q
   );

   //board debug interface
   assign led_o[7:0]=Q;
   // bcd8seg ia( .b(a), .h(hex_o[15:8]) );//output a to hex0
   // bcd8seg ib( .b(b), .h(hex_o[7:0]) );//output b to hex0
   // assign led_o[3:0] = s;
   // assign led_o[15:13]={carry,zero,overflow};


endmodule






   // initial for(integer i=0;i<8;i++) $display("top:%d %d %d ",a,b,s);

   // alu_tb#(4) i_tb
   // (
   // .b_o       (b) ,
   // .a_o       (a) ,
   // .sel_o     (sel) ,
   // .carry   (carry),//进位
   // .zero    (zero),//结果是否为0
   // .overflow(overflow),//溢出
   // .s       (s) //输出指示数码管
   // );

projects/shifter/random_seq_gen/vlt_dump.vcd
$version Generated by VerilatedVcd $end
$date Mon Apr 11 17:14:13 2022 $end
$timescale 1s $end

 $scope module TOP $end
  $var wire  1 # Clk $end
  $var wire  1 % Dout $end
  $var wire  8 $ Q [7:0] $end
  $var wire 16 ' hex_o [15:0] $end
  $var wire 16 & led_o [15:0] $end
  $scope module top $end
   $var wire  1 # Clk $end
   $var wire  1 % Dout $end
   $var wire  1 ( In_1 $end
   $var wire  1 ) In_2 $end
   $var wire  8 $ Q [7:0] $end
   $var wire 16 ' hex_o [15:0] $end
   $var wire 16 & led_o [15:0] $end
   $scope module i_shifter $end
    $var wire  1 # Clk $end
    $var wire  1 ) In $end
    $var wire  1 + L_R $end
    $var wire 32 * N [31:0] $end
    $var wire  8 $ Q [7:0] $end
   $upscope $end
  $upscope $end
 $upscope $end
$enddefinitions $end


#1
1#
b10000000 $
0%
b0000000010000000 &
b0000000000000000 '
0(
0)
b00000000000000000000000000001000 *
0+
#2
b01000000 $
b0000000001000000 &
#3
b00100000 $
b0000000000100000 &
#4
b00010000 $
b0000000000010000 &
1(
1)
#5
b10001000 $
b0000000010001000 &
#6
b11000100 $
b0000000011000100 &
#7
b11100010 $
b0000000011100010 &
0(
0)
#8
b01110001 $
b0000000001110001 &
#9
b00111000 $
b0000000000111000 &
#10
b00011100 $
b0000000000011100 &
1(
1)
#11
b10001110 $
b0000000010001110 &
0(
0)
#12
b01000111 $
b0000000001000111 &
#13
b00100011 $
b0000000000100011 &
1(
1)
#14
b10010001 $
b0000000010010001 &
0(
0)
#15
b01001000 $
b0000000001001000 &
1(
1)
#16
b10100100 $
b0000000010100100 &
#17
b11010010 $
b0000000011010010 &
#18
b11101001 $
b0000000011101001 &
0(
0)
#19
b01110100 $
b0000000001110100 &
#20
b00111010 $
b0000000000111010 &
#21
b00011101 $
b0000000000011101 &
#22
b00001110 $
b0000000000001110 &
#23
b00000111 $
b0000000000000111 &
#24
b00000011 $
b0000000000000011 &
1(
1)
#25
b10000001 $
b0000000010000001 &
#26
b11000000 $
b0000000011000000 &
0(
0)
#27
b01100000 $
b0000000001100000 &
#28
b00110000 $
b0000000000110000 &
1(
1)
#29
b10011000 $
b0000000010011000 &
0(
0)
#30
b01001100 $
b0000000001001100 &
#31
b00100110 $
b0000000000100110 &
1(
1)
#32
b10010011 $
b0000000010010011 &
0(
0)
#33
b01001001 $
b0000000001001001 &
#34
b00100100 $
b0000000000100100 &
1(
1)
#35
b10010010 $
b0000000010010010 &
#36
b11001001 $
b0000000011001001 &
0(
0)
#37
b01100100 $
b0000000001100100 &
1(
1)
#38
b10110010 $
b0000000010110010 &
#39
b11011001 $
b0000000011011001 &
#40
b11101100 $
b0000000011101100 &
0(
0)
#41
b01110110 $
b0000000001110110 &
#42
b00111011 $
b0000000000111011 &
1(
1)
#43
b10011101 $
b0000000010011101 &
0(
0)
#44
b01001110 $
b0000000001001110 &
#45
b00100111 $
b0000000000100111 &
#46
b00010011 $
b0000000000010011 &
#47
b00001001 $
b0000000000001001 &
#48
b00000100 $
b0000000000000100 &
1(
1)
#49
b10000010 $
b0000000010000010 &
0(
0)
#50
b01000001 $
b0000000001000001 &
1(
1)
#51
b10100000 $
b0000000010100000 &
0(
0)
#52
b01010000 $
b0000000001010000 &
1(
1)
#53
b10101000 $
b0000000010101000 &
#54
b11010100 $
b0000000011010100 &
0(
0)
#55
b01101010 $
b0000000001101010 &
1(
1)
#56
b10110101 $
b0000000010110101 &
#57
b11011010 $
b0000000011011010 &
0(
0)
#58
b01101101 $
b0000000001101101 &
1(
1)
#59
b10110110 $
b0000000010110110 &
0(
0)
#60
b01011011 $
b0000000001011011 &
1(
1)
#61
b10101101 $
b0000000010101101 &
#62
b11010110 $
b0000000011010110 &
0(
0)
#63
b01101011 $
b0000000001101011 &
#64
b00110101 $
b0000000000110101 &
1(
1)
#65
b10011010 $
b0000000010011010 &
0(
0)
#66
b01001101 $
b0000000001001101 &
1(
1)
#67
b10100110 $
b0000000010100110 &
#68
b11010011 $
b0000000011010011 &
0(
0)
#69
b01101001 $
b0000000001101001 &
#70
b00110100 $
b0000000000110100 &
#71
b00011010 $
b0000000000011010 &
#72
b00001101 $
b0000000000001101 &
1(
1)
#73
b10000110 $
b0000000010000110 &
#74
b11000011 $
b0000000011000011 &
#75
b11100001 $
b0000000011100001 &
#76
b11110000 $
b0000000011110000 &
#77
b11111000 $
b0000000011111000 &
0(
0)
#78
b01111100 $
b0000000001111100 &
1(
1)
#79
b10111110 $
b0000000010111110 &
#80
b11011111 $
b0000000011011111 &
0(
0)
#81
b01101111 $
b0000000001101111 &
1(
1)
#82
b10110111 $
b0000000010110111 &
#83
b11011011 $
b0000000011011011 &
#84
b11101101 $
b0000000011101101 &
#85
b11110110 $
b0000000011110110 &
0(
0)
#86
b01111011 $
b0000000001111011 &
1(
1)
#87
b10111101 $
b0000000010111101 &
0(
0)
#88
b01011110 $
b0000000001011110 &
1(
1)
#89
b10101111 $
b0000000010101111 &
#90
b11010111 $
b0000000011010111 &
#91
b11101011 $
b0000000011101011 &
0(
0)
#92
b01110101 $
b0000000001110101 &
1(
1)
#93
b10111010 $
b0000000010111010 &
0(
0)
#94
b01011101 $
b0000000001011101 &
#95
b00101110 $
b0000000000101110 &
#96
b00010111 $
b0000000000010111 &
1(
1)
#97
b10001011 $
b0000000010001011 &
0(
0)
#98
b01000101 $
b0000000001000101 &
#99
b00100010 $
b0000000000100010 &
#100
b00010001 $
b0000000000010001 &
#101
b00001000 $
b0000000000001000 &
1(
1)
#102
b10000100 $
b0000000010000100 &
#103
b11000010 $
b0000000011000010 &
0(
0)
#104
b01100001 $
b0000000001100001 &
1(
1)
#105
b10110000 $
b0000000010110000 &
#106
b11011000 $
b0000000011011000 &
0(
0)
#107
b01101100 $
b0000000001101100 &
#108
b00110110 $
b0000000000110110 &
#109
b00011011 $
b0000000000011011 &
1(
1)
#110
b10001101 $
b0000000010001101 &
#111
b11000110 $
b0000000011000110 &
#112
b11100011 $
b0000000011100011 &
#113
b11110001 $
b0000000011110001 &
0(
0)
#114
b01111000 $
b0000000001111000 &
#115
b00111100 $
b0000000000111100 &
1(
1)
#116
b10011110 $
b0000000010011110 &
#117
b11001111 $
b0000000011001111 &
#118
b11100111 $
b0000000011100111 &
0(
0)
#119
b01110011 $
b0000000001110011 &
#120
b00111001 $
b0000000000111001 &
1(
1)
#121
b10011100 $
b0000000010011100 &
#122
b11001110 $
b0000000011001110 &
0(
0)
#123
b01100111 $
b0000000001100111 &
#124
b00110011 $
b0000000000110011 &
#125
b00011001 $
b0000000000011001 &
1(
1)
#126
b10001100 $
b0000000010001100 &
0(
0)
#127
b01000110 $
b0000000001000110 &
1(
1)
#128
b10100011 $
b0000000010100011 &
#129
b11010001 $
b0000000011010001 &
0(
0)
#130
b01101000 $
b0000000001101000 &
1(
1)
#131
b10110100 $
b0000000010110100 &
0(
0)
#132
b01011010 $
b0000000001011010 &
#133
b00101101 $
b0000000000101101 &
1(
1)
#134
b10010110 $
b0000000010010110 &
0(
0)
#135
b01001011 $
b0000000001001011 &
#136
b00100101 $
b0000000000100101 &
#137
b00010010 $
b0000000000010010 &
1(
1)
#138
b10001001 $
b0000000010001001 &
0(
0)
#139
b01000100 $
b0000000001000100 &
1(
1)
#140
b10100010 $
b0000000010100010 &
0(
0)
#141
b01010001 $
b0000000001010001 &
#142
b00101000 $
b0000000000101000 &
1(
1)
#143
b10010100 $
b0000000010010100 &
0(
0)
#144
b01001010 $
b0000000001001010 &
1(
1)
#145
b10100101 $
b0000000010100101 &
0(
0)
#146
b01010010 $
b0000000001010010 &
1(
1)
#147
b10101001 $
b0000000010101001 &
0(
0)
#148
b01010100 $
b0000000001010100 &
#149
b00101010 $
b0000000000101010 &
1(
1)
#150
b10010101 $
b0000000010010101 &
#151
b11001010 $
b0000000011001010 &
#152
b11100101 $
b0000000011100101 &
0(
0)
#153
b01110010 $
b0000000001110010 &
1(
1)
#154
b10111001 $
b0000000010111001 &
#155
b11011100 $
b0000000011011100 &
#156
b11101110 $
b0000000011101110 &
0(
0)
#157
b01110111 $
b0000000001110111 &
1(
1)
#158
b10111011 $
b0000000010111011 &
#159
b11011101 $
b0000000011011101 &
0(
0)
#160
b01101110 $
b0000000001101110 &
#161
b00110111 $
b0000000000110111 &
1(
1)
#162
b10011011 $
b0000000010011011 &
#163
b11001101 $
b0000000011001101 &
#164
b11100110 $
b0000000011100110 &
#165
b11110011 $
b0000000011110011 &
0(
0)
#166
b01111001 $
b0000000001111001 &
1(
1)
#167
b10111100 $
b0000000010111100 &
#168
b11011110 $
b0000000011011110 &
#169
b11101111 $
b0000000011101111 &
#170
b11110111 $
b0000000011110111 &
#171
b11111011 $
b0000000011111011 &
#172
b11111101 $
b0000000011111101 &
0(
0)
#173
b01111110 $
b0000000001111110 &
1(
1)
#174
b10111111 $
b0000000010111111 &
0(
0)
#175
b01011111 $
b0000000001011111 &
#176
b00101111 $
b0000000000101111 &
1(
1)
#177
b10010111 $
b0000000010010111 &
#178
b11001011 $
b0000000011001011 &
0(
0)
#179
b01100101 $
b0000000001100101 &
#180
b00110010 $
b0000000000110010 &
1(
1)
#181
b10011001 $
b0000000010011001 &
#182
b11001100 $
b0000000011001100 &
0(
0)
#183
b01100110 $
b0000000001100110 &
1(
1)
#184
b10110011 $
b0000000010110011 &
0(
0)
#185
b01011001 $
b0000000001011001 &
1(
1)
#186
b10101100 $
b0000000010101100 &
0(
0)
#187
b01010110 $
b0000000001010110 &
#188
b00101011 $
b0000000000101011 &
#189
b00010101 $
b0000000000010101 &
1(
1)
#190
b10001010 $
b0000000010001010 &
#191
b11000101 $
b0000000011000101 &
0(
0)
#192
b01100010 $
b0000000001100010 &
#193
b00110001 $
b0000000000110001 &
#194
b00011000 $
b0000000000011000 &
#195
b00001100 $
b0000000000001100 &
#196
b00000110 $
b0000000000000110 &
1(
1)
#197
b10000011 $
b0000000010000011 &
#198
b11000001 $
b0000000011000001 &
#199
b11100000 $
b0000000011100000 &
0(
0)
#200
b01110000 $
b0000000001110000 &
1(
1)
#201
b10111000 $
b0000000010111000 &
0(
0)
#202
b01011100 $
b0000000001011100 &
1(
1)
#203
b10101110 $
b0000000010101110 &
0(
0)
#204
b01010111 $
b0000000001010111 &
1(
1)
#205
b10101011 $
b0000000010101011 &
0(
0)
#206
b01010101 $
b0000000001010101 &
1(
1)
#207
b10101010 $
b0000000010101010 &
#208
b11010101 $
b0000000011010101 &
#209
b11101010 $
b0000000011101010 &
#210
b11110101 $
b0000000011110101 &
#211
b11111010 $
b0000000011111010 &
0(
0)
#212
b01111101 $
b0000000001111101 &
#213
b00111110 $
b0000000000111110 &
1(
1)
#214
b10011111 $
b0000000010011111 &
0(
0)
#215
b01001111 $
b0000000001001111 &
1(
1)
#216
b10100111 $
b0000000010100111 &
0(
0)
#217
b01010011 $
b0000000001010011 &
#218
b00101001 $
b0000000000101001 &
#219
b00010100 $
b0000000000010100 &
#220
b00001010 $
b0000000000001010 &
1(
1)
#221
b10000101 $
b0000000010000101 &
0(
0)
#222
b01000010 $
b0000000001000010 &
#223
b00100001 $
b0000000000100001 &
1(
1)
#224
b10010000 $
b0000000010010000 &
#225
b11001000 $
b0000000011001000 &
#226
b11100100 $
b0000000011100100 &
#227
b11110010 $
b0000000011110010 &
#228
b11111001 $
b0000000011111001 &
#229
b11111100 $
b0000000011111100 &
#230
b11111110 $
b0000000011111110 &
#231
b11111111 $
b0000000011111111 &
0(
0)
#232
b01111111 $
b0000000001111111 &
#233
b00111111 $
b0000000000111111 &
#234
b00011111 $
b0000000000011111 &
#235
b00001111 $
b0000000000001111 &
1(
1)
#236
b10000111 $
b0000000010000111 &
0(
0)
#237
b01000011 $
b0000000001000011 &
1(
1)
#238
b10100001 $
b0000000010100001 &
#239
b11010000 $
b0000000011010000 &
#240
b11101000 $
b0000000011101000 &
#241
b11110100 $
b0000000011110100 &
0(
0)
#242
b01111010 $
b0000000001111010 &
#243
b00111101 $
b0000000000111101 &
#244
b00011110 $
b0000000000011110 &
1(
1)
#245
b10001111 $
b0000000010001111 &
#246
b11000111 $
b0000000011000111 &
0(
0)
#247
b01100011 $
b0000000001100011 &
1(
1)
#248
b10110001 $
b0000000010110001 &
0(
0)
#249
b01011000 $
b0000000001011000 &
#250
b00101100 $
b0000000000101100 &
#251
b00010110 $
b0000000000010110 &
#252
b00001011 $
b0000000000001011 &
#253
b00000101 $
b0000000000000101 &
#254
b00000010 $
b0000000000000010 &
#255
b00000001 $
b0000000000000001 &
1(
1)
#256
b10000000 $
b0000000010000000 &
0(
0)
#257
b01000000 $
b0000000001000000 &
#258
b00100000 $
b0000000000100000 &
#259
b00010000 $
b0000000000010000 &
1(
1)
#260
b10001000 $
b0000000010001000 &
#261
b11000100 $
b0000000011000100 &
#262
b11100010 $
b0000000011100010 &
0(
0)
#263
b01110001 $
b0000000001110001 &
#264
b00111000 $
b0000000000111000 &
#265
b00011100 $
b0000000000011100 &
1(
1)
#266
b10001110 $
b0000000010001110 &
0(
0)
#267
b01000111 $
b0000000001000111 &
#268
b00100011 $
b0000000000100011 &
1(
1)
#269
b10010001 $
b0000000010010001 &
0(
0)
#270
b01001000 $
b0000000001001000 &
1(
1)
#271
b10100100 $
b0000000010100100 &
#272
b11010010 $
b0000000011010010 &
#273
b11101001 $
b0000000011101001 &
0(
0)
#274
b01110100 $
b0000000001110100 &
#275
b00111010 $
b0000000000111010 &
#276
b00011101 $
b0000000000011101 &
#277
b00001110 $
b0000000000001110 &
#278
b00000111 $
b0000000000000111 &
#279
b00000011 $
b0000000000000011 &
1(
1)
#280
b10000001 $
b0000000010000001 &
#281
b11000000 $
b0000000011000000 &
0(
0)
#282
b01100000 $
b0000000001100000 &
#283
b00110000 $
b0000000000110000 &
1(
1)
#284
b10011000 $
b0000000010011000 &
0(
0)
#285
b01001100 $
b0000000001001100 &
#286
b00100110 $
b0000000000100110 &
1(
1)
#287
b10010011 $
b0000000010010011 &
0(
0)
#288
b01001001 $
b0000000001001001 &
#289
b00100100 $
b0000000000100100 &
1(
1)
#290
b10010010 $
b0000000010010010 &
#291
b11001001 $
b0000000011001001 &
0(
0)
#292
b01100100 $
b0000000001100100 &
1(
1)
#293
b10110010 $
b0000000010110010 &
#294
b11011001 $
b0000000011011001 &
#295
b11101100 $
b0000000011101100 &
0(
0)
#296
b01110110 $
b0000000001110110 &
#297
b00111011 $
b0000000000111011 &
1(
1)
#298
b10011101 $
b0000000010011101 &
0(
0)
#299
b01001110 $
b0000000001001110 &
#300
b00100111 $
b0000000000100111 &
#301
b00010011 $
b0000000000010011 &
#302
b00001001 $
b0000000000001001 &
#303
b00000100 $
b0000000000000100 &
1(
1)
#304
b10000010 $
b0000000010000010 &
0(
0)
#305
b01000001 $
b0000000001000001 &
1(
1)
#306
b10100000 $
b0000000010100000 &
0(
0)
#307
b01010000 $
b0000000001010000 &
1(
1)
#308
b10101000 $
b0000000010101000 &
#309
b11010100 $
b0000000011010100 &
0(
0)
#310
b01101010 $
b0000000001101010 &
1(
1)
#311
b10110101 $
b0000000010110101 &
#312
b11011010 $
b0000000011011010 &
0(
0)
#313
b01101101 $
b0000000001101101 &
1(
1)
#314
b10110110 $
b0000000010110110 &
0(
0)
#315
b01011011 $
b0000000001011011 &
1(
1)
#316
b10101101 $
b0000000010101101 &
#317
b11010110 $
b0000000011010110 &
0(
0)
#318
b01101011 $
b0000000001101011 &
#319
b00110101 $
b0000000000110101 &
1(
1)
#320
b10011010 $
b0000000010011010 &
0(
0)
#321
b01001101 $
b0000000001001101 &
1(
1)
#322
b10100110 $
b0000000010100110 &
#323
b11010011 $
b0000000011010011 &
0(
0)
#324
b01101001 $
b0000000001101001 &
#325
b00110100 $
b0000000000110100 &
#326
b00011010 $
b0000000000011010 &
#327
b00001101 $
b0000000000001101 &
1(
1)
#328
b10000110 $
b0000000010000110 &
#329
b11000011 $
b0000000011000011 &
#330
b11100001 $
b0000000011100001 &
#331
b11110000 $
b0000000011110000 &
#332
b11111000 $
b0000000011111000 &
0(
0)
#333
b01111100 $
b0000000001111100 &
1(
1)
#334
b10111110 $
b0000000010111110 &
#335
b11011111 $
b0000000011011111 &
0(
0)
#336
b01101111 $
b0000000001101111 &
1(
1)
#337
b10110111 $
b0000000010110111 &
#338
b11011011 $
b0000000011011011 &
#339
b11101101 $
b0000000011101101 &
#340
b11110110 $
b0000000011110110 &
0(
0)
#341
b01111011 $
b0000000001111011 &
1(
1)
#342
b10111101 $
b0000000010111101 &
0(
0)
#343
b01011110 $
b0000000001011110 &
1(
1)
#344
b10101111 $
b0000000010101111 &
#345
b11010111 $
b0000000011010111 &
#346
b11101011 $
b0000000011101011 &
0(
0)
#347
b01110101 $
b0000000001110101 &
1(
1)
#348
b10111010 $
b0000000010111010 &
0(
0)
#349
b01011101 $
b0000000001011101 &
#350
b00101110 $
b0000000000101110 &
#351
b00010111 $
b0000000000010111 &
1(
1)
#352
b10001011 $
b0000000010001011 &
0(
0)
#353
b01000101 $
b0000000001000101 &
#354
b00100010 $
b0000000000100010 &
#355
b00010001 $
b0000000000010001 &
#356
b00001000 $
b0000000000001000 &
1(
1)
#357
b10000100 $
b0000000010000100 &
#358
b11000010 $
b0000000011000010 &
0(
0)
#359
b01100001 $
b0000000001100001 &
1(
1)
#360
b10110000 $
b0000000010110000 &
#361
b11011000 $
b0000000011011000 &
0(
0)
#362
b01101100 $
b0000000001101100 &
#363
b00110110 $
b0000000000110110 &
#364
b00011011 $
b0000000000011011 &
1(
1)
#365
b10001101 $
b0000000010001101 &
#366
b11000110 $
b0000000011000110 &
#367
b11100011 $
b0000000011100011 &
#368
b11110001 $
b0000000011110001 &
0(
0)
#369
b01111000 $
b0000000001111000 &
#370
b00111100 $
b0000000000111100 &
1(
1)
#371
b10011110 $
b0000000010011110 &
#372
b11001111 $
b0000000011001111 &
#373
b11100111 $
b0000000011100111 &
0(
0)
#374
b01110011 $
b0000000001110011 &
#375
b00111001 $
b0000000000111001 &
1(
1)
#376
b10011100 $
b0000000010011100 &
#377
b11001110 $
b0000000011001110 &
0(
0)
#378
b01100111 $
b0000000001100111 &
#379
b00110011 $
b0000000000110011 &
#380
b00011001 $
b0000000000011001 &
1(
1)
#381
b10001100 $
b0000000010001100 &
0(
0)
#382
b01000110 $
b0000000001000110 &
1(
1)
#383
b10100011 $
b0000000010100011 &
#384
b11010001 $
b0000000011010001 &
0(
0)
#385
b01101000 $
b0000000001101000 &
1(
1)
#386
b10110100 $
b0000000010110100 &
0(
0)
#387
b01011010 $
b0000000001011010 &
#388
b00101101 $
b0000000000101101 &
1(
1)
#389
b10010110 $
b0000000010010110 &
0(
0)
#390
b01001011 $
b0000000001001011 &
#391
b00100101 $
b0000000000100101 &
#392
b00010010 $
b0000000000010010 &
1(
1)
#393
b10001001 $
b0000000010001001 &
0(
0)
#394
b01000100 $
b0000000001000100 &
1(
1)
#395
b10100010 $
b0000000010100010 &
0(
0)
#396
b01010001 $
b0000000001010001 &
#397
b00101000 $
b0000000000101000 &
1(
1)
#398
b10010100 $
b0000000010010100 &
0(
0)
#399
b01001010 $
b0000000001001010 &
1(
1)
#400
b10100101 $
b0000000010100101 &
0(
0)
#401
b01010010 $
b0000000001010010 &
1(
1)
#402
b10101001 $
b0000000010101001 &
0(
0)
#403
b01010100 $
b0000000001010100 &
#404
b00101010 $
b0000000000101010 &
1(
1)
#405
b10010101 $
b0000000010010101 &
#406
b11001010 $
b0000000011001010 &
#407
b11100101 $
b0000000011100101 &
0(
0)
#408
b01110010 $
b0000000001110010 &
1(
1)
#409
b10111001 $
b0000000010111001 &
#410
b11011100 $
b0000000011011100 &
#411
b11101110 $
b0000000011101110 &
0(
0)
#412
b01110111 $
b0000000001110111 &
1(
1)
#413
b10111011 $
b0000000010111011 &
#414
b11011101 $
b0000000011011101 &
0(
0)
#415
b01101110 $
b0000000001101110 &
#416
b00110111 $
b0000000000110111 &
1(
1)
#417
b10011011 $
b0000000010011011 &
#418
b11001101 $
b0000000011001101 &
#419
b11100110 $
b0000000011100110 &
#420
b11110011 $
b0000000011110011 &
0(
0)
#421
b01111001 $
b0000000001111001 &
1(
1)
#422
b10111100 $
b0000000010111100 &
#423
b11011110 $
b0000000011011110 &
#424
b11101111 $
b0000000011101111 &
#425
b11110111 $
b0000000011110111 &
#426
b11111011 $
b0000000011111011 &
#427
b11111101 $
b0000000011111101 &
0(
0)
#428
b01111110 $
b0000000001111110 &
1(
1)
#429
b10111111 $
b0000000010111111 &
0(
0)
#430
b01011111 $
b0000000001011111 &
#431
b00101111 $
b0000000000101111 &
1(
1)
#432
b10010111 $
b0000000010010111 &
#433
b11001011 $
b0000000011001011 &
0(
0)
#434
b01100101 $
b0000000001100101 &
#435
b00110010 $
b0000000000110010 &
1(
1)
#436
b10011001 $
b0000000010011001 &
#437
b11001100 $
b0000000011001100 &
0(
0)
#438
b01100110 $
b0000000001100110 &
1(
1)
#439
b10110011 $
b0000000010110011 &
0(
0)
#440
b01011001 $
b0000000001011001 &
1(
1)
#441
b10101100 $
b0000000010101100 &
0(
0)
#442
b01010110 $
b0000000001010110 &
#443
b00101011 $
b0000000000101011 &
#444
b00010101 $
b0000000000010101 &
1(
1)
#445
b10001010 $
b0000000010001010 &
#446
b11000101 $
b0000000011000101 &
0(
0)
#447
b01100010 $
b0000000001100010 &
#448
b00110001 $
b0000000000110001 &
#449
b00011000 $
b0000000000011000 &
#450
b00001100 $
b0000000000001100 &
#451
b00000110 $
b0000000000000110 &
1(
1)
#452
b10000011 $
b0000000010000011 &
#453
b11000001 $
b0000000011000001 &
#454
b11100000 $
b0000000011100000 &
0(
0)
#455
b01110000 $
b0000000001110000 &
1(
1)
#456
b10111000 $
b0000000010111000 &
0(
0)
#457
b01011100 $
b0000000001011100 &
1(
1)
#458
b10101110 $
b0000000010101110 &
0(
0)
#459
b01010111 $
b0000000001010111 &
1(
1)
#460
b10101011 $
b0000000010101011 &
0(
0)
#461
b01010101 $
b0000000001010101 &
1(
1)
#462
b10101010 $
b0000000010101010 &
#463
b11010101 $
b0000000011010101 &
#464
b11101010 $
b0000000011101010 &
#465
b11110101 $
b0000000011110101 &
#466
b11111010 $
b0000000011111010 &
0(
0)
#467
b01111101 $
b0000000001111101 &
#468
b00111110 $
b0000000000111110 &
1(
1)
#469
b10011111 $
b0000000010011111 &
0(
0)
#470
b01001111 $
b0000000001001111 &
1(
1)
#471
b10100111 $
b0000000010100111 &
0(
0)
#472
b01010011 $
b0000000001010011 &
#473
b00101001 $
b0000000000101001 &
#474
b00010100 $
b0000000000010100 &
#475
b00001010 $
b0000000000001010 &
1(
1)
#476
b10000101 $
b0000000010000101 &
0(
0)
#477
b01000010 $
b0000000001000010 &
#478
b00100001 $
b0000000000100001 &
1(
1)
#479
b10010000 $
b0000000010010000 &
#480
b11001000 $
b0000000011001000 &
#481
b11100100 $
b0000000011100100 &
#482
b11110010 $
b0000000011110010 &
#483
b11111001 $
b0000000011111001 &
#484
b11111100 $
b0000000011111100 &
#485
b11111110 $
b0000000011111110 &
#486
b11111111 $
b0000000011111111 &
0(
0)
#487
b01111111 $
b0000000001111111 &
#488
b00111111 $
b0000000000111111 &
#489
b00011111 $
b0000000000011111 &
#490
b00001111 $
b0000000000001111 &
1(
1)
#491
b10000111 $
b0000000010000111 &
0(
0)
#492
b01000011 $
b0000000001000011 &
1(
1)
#493
b10100001 $
b0000000010100001 &
#494
b11010000 $
b0000000011010000 &
#495
b11101000 $
b0000000011101000 &
#496
b11110100 $
b0000000011110100 &
0(
0)
#497
b01111010 $
b0000000001111010 &
#498
b00111101 $
b0000000000111101 &
#499
b00011110 $
b0000000000011110 &
1(
1)
#500
b10001111 $
b0000000010001111 &
#501
b11000111 $
b0000000011000111 &
0(
0)
#502
b01100011 $
b0000000001100011 &
1(
1)
#503
b10110001 $
b0000000010110001 &
0(
0)
#504
b01011000 $
b0000000001011000 &
#505
b00101100 $
b0000000000101100 &
#506
b00010110 $
b0000000000010110 &
#507
b00001011 $
b0000000000001011 &
#508
b00000101 $
b0000000000000101 &
#509
b00000010 $
b0000000000000010 &
#510
b00000001 $
b0000000000000001 &
1(
1)
#511
b10000000 $
b0000000010000000 &
0(
0)
#512
b01000000 $
b0000000001000000 &
#513
b00100000 $
b0000000000100000 &
