projects/xor_gate/xor_gate.v
`timescale 1ms/1ps
module xor_gate(
  input a,
  input b,
  output f
);
    initial begin
        $dumpfile("./vlt_dump.vcd");
        $dumpvars(1,xor_gate);
    end
    assign f = a ^ b;
endmodule

projects/xor_gate/vlt_dump.vcd
$version Generated by VerilatedVcd $end
$date Mon Apr  4 20:42:49 2022 $end
$timescale 1ps $end

 $scope module TOP $end
  $var wire  1 # a $end
  $var wire  1 $ b $end
  $var wire  1 % f $end
  $scope module xor_gate $end
   $var wire  1 # a $end
   $var wire  1 $ b $end
   $var wire  1 % f $end
  $upscope $end
 $upscope $end
$enddefinitions $end


#0
1#
0$
1%
#1
1$
0%
#2
#3
0#
0$
#4
1#
1$
#5
0#
1%
#6
#7
1#
0$
#8
0#
0%
#9
#10
1#
1%
#11
1$
0%
#12
0#
0$
#13
1$
1%
#14
1#
0%
#15
0$
1%
#16
0#
0%
#17
1#
1$
#18
0$
1%
#19
#20
1$
0%
#21
#22
0#
1%
#23
0$
0%
#24
1#
1%
#25
#26
#27
0#
1$
#28
0$
0%
#29
1$
1%
#30
1#
0%
#31
0#
1%
#32
#33
#34
1#
0%
#35
0#
1%
#36
#37
#38
0$
0%
#39
1#
1%
#40
#41
0#
0%
#42
#43
1#
1$
#44
0#
1%
#45
0$
0%
#46
#47
1#
1%
#48
0#
0%
#49
1$
1%
#50
1#
0$
#51
0#
0%
#52
1#
1$
#53
0$
1%
#54
#55
0#
0%
#56
1#
1%
#57
0#
1$
#58
1#
0%
#59
0#
1%
#60
#61
1#
0%
#62
#63
#64
#65
0$
1%
#66
1$
0%
#67
0#
1%
#68
#69
1#
0$
#70
0#
1$
#71
#72
1#
0%
#73
0#
0$
#74
1$
1%
#75
#76
#77
#78
#79
1#
0%
#80
0$
1%
#81
0#
0%
#82
1#
1%
#83
#84
0#
0%
#85
#86
1#
1%
#87
1$
0%
#88
#89
0$
1%
#90
0#
1$
#91
1#
0$
#92
1$
0%
#93
0#
1%
#94
#95
1#
0%
#96
#97
0#
0$
#98
1#
1$
#99
0#
1%
#100
0$
0%
#101
1#
1$
#102
0$
1%
#103
0#
0%
#104
#105
#106
1#
1$
#107
0$
1%
#108
0#
1$
#109
#110
#111
#112
0$
0%
#113
1#
1$
#114
0#
0$
#115
1#
1%
#116
0#
0%
#117
1#
1$
#118
0$
1%
#119
0#
1$
#120
0$
0%
#121
1#
1$
#122
0#
0$
#123
#124
1#
1%
#125
1$
0%
#126
0$
1%
#127
0#
1$
#128
0$
0%
#129
#130
1$
1%
#131
0$
0%
#132
#133
1$
1%
#134
0$
0%
#135
#136
1$
1%
#137
1#
0$
#138
0#
1$
#139
1#
0%
#140
0$
1%
#141
#142
0#
1$
#143
1#
0%
#144
0$
1%
#145
1$
0%
#146
0$
1%
#147
0#
1$
#148
0$
0%
#149
#150
#151
#152
1$
1%
#153
1#
0$
#154
#155
#156
0#
0%
#157
1#
1$
#158
0#
0$
#159
1$
1%
#160
#161
1#
0$
#162
1$
0%
#163
#164
0$
1%
#165
1$
0%
#166
0#
1%
#167
1#
0$
#168
#169
0#
0%
#170
#171
1$
1%
#172
#173
0$
0%
#174
#175
#176
1#
1$
#177
0#
1%
#178
0$
0%
#179
1$
1%
#180
0$
0%
#181
#182
1#
1$
#183
0$
1%
#184
0#
1$
#185
0$
0%
#186
1#
1$
#187
0$
1%
#188
0#
1$
#189
0$
0%
#190
1#
1%
#191
1$
0%
#192
#193
0#
1%
#194
1#
0$
#195
0#
1$
#196
0$
0%
#197
#198
1$
1%
#199
0$
0%
#200
1$
1%
#201
0$
0%
#202
#203
#204
1#
1%
#205
1$
0%
#206
0$
1%
#207
0#
0%
#208
1#
1%
#209
0#
1$
#210
0$
0%
#211
1$
1%
#212
1#
0$
#213
1$
0%
#214
#215
0$
1%
#216
0#
1$
#217
0$
0%
#218
1#
1%
#219
1$
0%
#220
0#
0$
#221
1$
1%
#222
0$
0%
#223
1$
1%
#224
0$
0%
#225
#226
1$
1%
#227
1#
0%
#228
0$
1%
#229
0#
1$
#230
#231
1#
0$
#232
1$
0%
#233
0$
1%
#234
#235
1$
0%
#236
0#
1%
#237
1#
0$
#238
1$
0%
#239
#240
0$
1%
#241
0#
1$
#242
1#
0%
#243
0$
1%
#244
0#
1$
#245
1#
0$
#246
#247
0#
0%
#248
1#
1$
#249
0#
0$
#250
1#
1%
#251
0#
1$
#252
1#
0%
#253
#254
0#
1%
#255
#256
1#
0$
#257
0#
0%
#258
1$
1%
#259
0$
0%
#260
1#
1%
#261
0#
0%
#262
#263
#264
#265
1$
1%
#266
0$
0%
#267
1#
1%
#268
#269
1$
0%
#270
#271
0#
0$
#272
1$
1%
#273
0$
0%
#274
1$
1%
#275
#276
1#
0$
#277
1$
0%
#278
0#
1%
#279
1#
0$
#280
0#
0%
#281
#282
1$
1%
#283
0$
0%
#284
1#
1$
#285
#286
0$
1%
#287
1$
0%
#288
0$
1%
#289
1$
0%
#290
#291
0$
1%
#292
#293
1$
0%
#294
0#
1%
#295
0$
0%
#296
1#
1%
#297
0#
1$
#298
1#
0%
#299
0$
1%
#300
0#
1$
#301
1#
0%
#302
#303
0#
0$
#304
1#
1$
#305
0$
1%
#306
0#
0%
#307
1$
1%
#308
1#
0%
#309
#310
0#
1%
#311
1#
0%
#312
#313
0$
1%
#314
0#
0%
#315
1$
1%
#316
1#
0$
#317
0#
0%
#318
1#
1$
#319
0#
0$
#320
#321
1$
1%
#322
0$
0%
#323
1$
1%
#324
1#
0%
#325
0#
0$
#326
1$
1%
#327
1#
0%
#328
0$
1%
#329
1$
0%
#330
0$
1%
#331
0#
0%
#332
1$
1%
#333
1#
0%
#334
0#
1%
#335
1#
0$
#336
1$
0%
#337
0$
1%
#338
#339
#340
#341
0#
0%
#342
1#
1%
#343
#344
0#
1$
#345
#346
1#
0$
#347
0#
1$
#348
1#
0%
#349
0#
1%
#350
#351
0$
0%
#352
1$
1%
#353
#354
1#
0%
#355
#356
0$
1%
#357
1$
0%
#358
0#
0$
#359
1#
1%
#360
1$
0%
#361
0#
0$
#362
#363
1#
1$
#364
#365
#366
0#
1%
#367
1#
0$
#368
0#
1$
#369
1#
0$
#370
1$
0%
#371
0$
1%
#372
#373
1$
0%
#374
0#
1%
#375
1#
0$
#376
0#
1$
#377
0$
0%
#378
1#
1%
#379
0#
0%
#380
1#
1$
#381
0#
0$
#382
1$
1%
#383
0$
0%
#384
1#
1%
#385
0#
0%
#386
1#
1$
#387
0#
0$
#388
1#
1%
#389
#390
#391
0#
1$
#392
0$
0%
#393
1$
1%
#394
0$
0%
#395
#396
1#
1%
#397
0#
1$
#398
1#
0$
#399
#400
0#
0%
#401
1$
1%
#402
1#
0%
#403
#404
0$
1%
#405
#406
1$
0%
#407
#408
#409
0#
0$
#410
1#
1%
#411
0#
0%
#412
#413
1#
1%
#414
0#
1$
#415
#416
1#
0%
#417
0#
0$
#418
#419
1#
1$
#420
0#
0$
#421
1#
1$
#422
0$
1%
#423
0#
1$
#424
#425
1#
0%
#426
#427
0#
0$
#428
1#
1$
#429
0#
1%
#430
0$
0%
#431
1$
1%
#432
1#
0%
#433
0#
1%
#434
1#
0%
#435
0#
1%
#436
#437
1#
0%
#438
0#
1%
#439
0$
0%
#440
1$
1%
#441
1#
0$
#442
0#
1$
#443
#444
1#
0$
#445
1$
0%
#446
0#
1%
#447
1#
0$
#448
0#
1$
#449
1#
0%
#450
0#
0$
#451
1#
1%
#452
#453
0#
1$
#454
1#
0$
#455
#456
0#
1$
#457
0$
0%
#458
#459
1$
1%
#460
#461
1#
0$
#462
0#
0%
#463
1$
1%
#464
1#
0$
#465
0#
1$
#466
#467
#468
1#
0$
#469
1$
0%
#470
0#
0$
#471
1#
1%
#472
1$
0%
#473
0$
1%
#474
1$
0%
#475
#476
0#
0$
#477
1#
1%
#478
0#
0%
#479
1#
1$
#480
0#
0$
#481
1#
1%
#482
1$
0%
#483
#484
0$
1%
#485
0#
1$
#486
1#
0%
#487
0#
0$
#488
1$
1%
#489
#490
0$
0%
#491
#492
1$
1%
#493
#494
1#
0$
#495
0#
1$
#496
#497
1#
0%
#498
0#
1%
#499
#500
1#
0$
#501
#502
1$
0%
#503
#504
0#
1%
#505
0$
0%
#506
1#
1%
#507
0#
0%
#508
#509
1#
1$
#510
0#
1%
#511
1#
0$
#512
#513
0#
1$
#514
1#
0$
#515
1$
0%
#516
0$
1%
#517
#518
#519
0#
1$
#520
0$
0%
#521
1#
1$
#522
#523
#524
0$
1%
#525
0#
0%
#526
1$
1%
#527
#528
0$
0%
#529
1$
1%
#530
1#
0%
#531
0#
0$
#532
1#
1%
#533
0#
0%
#534
#535
1#
1%
#536
#537
0#
0%
#538
1#
1$
#539
#540
0#
1%
#541
1#
0$
#542
1$
0%
#543
#544
0#
1%
#545
#546
1#
0%
#547
0$
1%
#548
1$
0%
#549
#550
0#
0$
#551
1$
1%
#552
1#
0$
#553
#554
#555
1$
0%
#556
0$
1%
#557
#558
0#
0%
#559
1#
1%
#560
0#
0%
#561
1#
1$
#562
0$
1%
#563
#564
#565
1$
0%
#566
#567
0#
0$
#568
1#
1$
#569
0#
1%
#570
1#
0$
#571
0#
1$
#572
0$
0%
#573
1#
1%
#574
0#
1$
#575
0$
0%
#576
1#
1$
#577
0$
1%
#578
1$
0%
#579
0#
1%
#580
1#
0%
#581
0#
0$
#582
1#
1$
#583
0#
0$
#584
1$
1%
#585
1#
0$
#586
#587
1$
0%
#588
0#
0$
#589
#590
1#
1%
#591
#592
0#
0%
#593
1$
1%
#594
1#
0$
#595
0#
1$
#596
#597
1#
0%
#598
0#
0$
#599
1#
1%
#600
1$
0%
#601
0#
0$
#602
1#
1$
#603
#604
0#
1%
#605
1#
0%
#606
0#
0$
#607
#608
1#
1%
#609
#610
#611
1$
0%
#612
#613
0#
1%
#614
1#
0%
#615
0$
1%
#616
0#
0%
#617
1$
1%
#618
1#
0%
#619
0#
1%
#620
1#
0$
#621
1$
0%
#622
0#
1%
#623
1#
0%
#624
0$
1%
#625
0#
0%
#626
1$
1%
#627
1#
0%
#628
0#
1%
#629
#630
1#
0$
#631
1$
0%
#632
0#
1%
#633
1#
0%
#634
#635
0$
1%
#636
#637
#638
#639
#640
0#
1$
#641
1#
0%
#642
0$
1%
#643
0#
1$
#644
#645
1#
0%
#646
0$
1%
#647
0#
1$
#648
#649
#650
1#
0%
#651
0$
1%
#652
#653
0#
0%
#654
#655
1#
1%
#656
#657
#658
0#
0%
#659
#660
1#
1$
#661
0$
1%
#662
#663
1$
0%
#664
#665
0#
0$
#666
1#
1$
#667
0$
1%
#668
1$
0%
#669
#670
0$
1%
#671
0#
1$
#672
#673
1#
0$
#674
1$
0%
#675
0$
1%
#676
0#
0%
#677
#678
1$
1%
#679
1#
0$
#680
#681
0#
0%
#682
1#
1$
#683
0#
1%
#684
1#
0%
#685
0#
0$
#686
1#
1%
#687
1$
0%
#688
0#
1%
#689
#690
#691
#692
1#
0$
#693
#694
0#
0%
#695
1$
1%
#696
0$
0%
#697
1#
1%
#698
0#
1$
#699
1#
0%
#700
#701
0$
1%
#702
0#
1$
#703
0$
0%
#704
#705
1#
1%
#706
1$
0%
#707
0$
1%
#708
0#
0%
#709
#710
1#
1%
#711
1$
0%
#712
0$
1%
#713
1$
0%
#714
0$
1%
#715
0#
0%
#716
1$
1%
#717
1#
0$
#718
0#
1$
#719
0$
0%
#720
1#
1$
#721
0$
1%
#722
#723
0#
1$
#724
1#
0%
#725
0$
1%
#726
#727
#728
0#
1$
#729
1#
0%
#730
#731
0#
1%
#732
1#
0%
#733
#734
0#
1%
#735
#736
1#
0%
#737
0$
1%
#738
1$
0%
#739
0$
1%
#740
0#
0%
#741
#742
#743
#744
1#
1%
#745
#746
1$
0%
#747
0#
0$
#748
1$
1%
#749
0$
0%
#750
1#
1%
#751
#752
#753
0#
0%
#754
1$
1%
#755
1#
0$
#756
1$
0%
#757
0#
1%
#758
1#
0%
#759
0$
1%
#760
#761
#762
0#
1$
#763
1#
0$
#764
0#
1$
#765
1#
0%
#766
0$
1%
#767
#768
1$
0%
#769
0#
1%
#770
#771
1#
0%
#772
0$
1%
#773
0#
0%
#774
1#
1$
#775
0$
1%
#776
0#
0%
#777
#778
1#
1$
#779
0#
1%
#780
#781
1#
0%
#782
0#
0$
#783
1#
1$
#784
0#
0$
#785
#786
1#
1$
#787
0#
0$
#788
1#
1%
#789
#790
0#
0%
#791
#792
1$
1%
#793
#794
0$
0%
#795
1$
1%
#796
#797
0$
0%
#798
#799
1#
1%
#800
0#
1$
#801
#802
0$
0%
#803
#804
1#
1$
#805
0#
1%
#806
1#
0%
#807
#808
0#
1%
#809
0$
0%
#810
1#
1%
#811
1$
0%
#812
0#
0$
#813
1#
1%
#814
0#
0%
#815
#816
1#
1%
#817
#818
1$
0%
#819
0#
0$
#820
#821
1#
1$
#822
0$
1%
#823
0#
1$
#824
1#
0$
#825
0#
0%
#826
1#
1$
#827
0#
1%
#828
1#
0%
#829
#830
0#
1%
#831
1#
0%
#832
#833
0$
1%
#834
0#
1$
#835
#836
#837
#838
1#
0%
#839
0$
1%
#840
1$
0%
#841
0$
1%
#842
0#
1$
#843
1#
0$
#844
0#
0%
#845
1#
1%
#846
1$
0%
#847
0#
1%
#848
#849
1#
0$
#850
#851
1$
0%
#852
0$
1%
#853
0#
1$
#854
1#
0%
#855
0$
1%
#856
0#
0%
#857
1#
1$
#858
0$
1%
#859
#860
#861
0#
0%
#862
1#
1%
#863
1$
0%
#864
0#
1%
#865
#866
1#
0%
#867
0#
0$
#868
1#
1%
#869
#870
0#
1$
#871
1#
0$
#872
#873
1$
0%
#874
0#
0$
#875
1#
1$
#876
#877
0#
0$
#878
1$
1%
#879
0$
0%
#880
#881
1#
1$
#882
#883
0#
1%
#884
1#
0%
#885
#886
0#
0$
#887
#888
1$
1%
#889
1#
0%
#890
0#
0$
#891
1$
1%
#892
1#
0$
#893
1$
0%
#894
0#
1%
#895
1#
0$
#896
#897
0#
1$
#898
1#
0$
#899
0#
1$
#900
1#
0%
#901
0#
0$
#902
#903
#904
1$
1%
#905
1#
0$
#906
#907
#908
0#
0%
#909
#910
1$
1%
#911
1#
0%
#912
0#
1%
#913
#914
1#
0$
#915
0#
0%
#916
1$
1%
#917
0$
0%
#918
1#
1%
#919
0#
1$
#920
1#
0$
#921
#922
0#
0%
#923
1#
1%
#924
1$
0%
#925
#926
0#
0$
#927
#928
1#
1$
#929
0#
0$
#930
1#
1%
#931
0#
1$
#932
1#
0%
#933
#934
0$
1%
#935
0#
1$
#936
0$
0%
#937
1#
1%
#938
0#
0%
#939
1$
1%
#940
1#
0%
#941
0#
0$
#942
1#
1$
#943
0#
0$
#944
#945
1$
1%
#946
1#
0%
#947
0$
1%
#948
0#
0%
#949
1#
1$
#950
0#
0$
#951
#952
#953
#954
1$
1%
#955
0$
0%
#956
#957
#958
1#
1%
#959
0#
1$
#960
1#
0%
#961
0$
1%
#962
0#
0%
#963
#964
#965
1#
1$
#966
0#
0$
#967
1#
1%
#968
0#
0%
#969
#970
1#
1%
#971
0#
1$
#972
1#
0$
#973
#974
#975
0#
0%
#976
1#
1$
#977
0#
1%
#978
1#
0$
#979
1$
0%
#980
0#
0$
#981
#982
#983
#984
1$
1%
#985
1#
0%
#986
#987
0#
0$
#988
#989
1#
1$
#990
0#
1%
#991
1#
0%
#992
0#
1%
#993
#994
1#
0%
#995
0#
0$
#996
1#
1$
#997
0#
0$
#998
1#
1$
#999
0#
1%
